[
  {
    "codigo_inep": "13395",
    "nome_curso": "ADMINISTRAÇÃO",
    "grau": "BACHARELADO",
    "turno": "Matutino e Vespertino",
    "campus": "João Pessoa",
    "area_conhecimento": "Ciências Sociais Aplicadas",
    "area_conhecimento_vestibular": "Área IV - CIÊNCIAS HUMANAS E SOCIAIS",
    "modalidade": "Presencial",
    "unidade_responsavel": "CENTRO DE CIÊNCIAS SOCIAIS E APLICADAS (CCSA)",
    "unidade_coordenacao": "CCSA - COORDENAÇÃO DE ADMINISTRAÇÃO"
  },
  {
    "codigo_inep": "13395",
    "nome_curso": "ADMINISTRAÇÃO",
    "grau": "BACHARELADO",
    "turno": "Noturno",
    "campus": "João Pessoa",
    "area_conhecimento": "Ciências Sociais Aplicadas",
    "area_conhecimento_vestibular": "Área IV - CIÊNCIAS HUMANAS E SOCIAIS",
    "modalidade": "Presencial",
    "unidade_responsavel": "CENTRO DE CIÊNCIAS SOCIAIS E APLICADAS (CCSA)",
    "unidade_coordenacao": "CCSA - COORDENAÇÃO DE ADMINISTRAÇÃO"
  },
  {
    "codigo_inep": "13455",
    "nome_curso": "ADMINISTRAÇÃO",
    "grau": "BACHARELADO",
    "turno": "Matutino e Vespertino",
    "campus": "Bananeiras",
    "area_conhecimento": "Ciências Sociais Aplicadas",
    "area_conhecimento_vestibular": "Área IV - CIÊNCIAS HUMANAS E SOCIAIS",
    "modalidade": "Presencial",
    "unidade_responsavel": "CENTRO DE CIÊNCIAS HUMANAS SOCIAIS E AGRÁRIAS (CCHSA)",
    "unidade_coordenacao": "CCHSA - COORDENAÇÃO DE ADMINISTRAÇÃO"
  },
  {
    "codigo_inep": "13455",
    "nome_curso": "ADMINISTRAÇÃO",
    "grau": "BACHARELADO",
    "turno": "Noturno",
    "campus": "Bananeiras",
    "area_conhecimento": "Ciências Sociais Aplicadas",
    "area_conhecimento_vestibular": "Área IV - CIÊNCIAS HUMANAS E SOCIAIS",
    "modalidade": "Presencial",
    "unidade_responsavel": "CENTRO DE CIÊNCIAS HUMANAS SOCIAIS E AGRÁRIAS (CCHSA)",
    "unidade_coordenacao": "CCHSA - COORDENAÇÃO DE ADMINISTRAÇÃO"
  },
  {
    "codigo_inep": "1440696",
    "nome_curso": "ADMINISTRAÇÃO",
    "grau": "BACHARELADO",
    "turno": "Matutino e Vespertino",
    "campus": "Litoral Norte (Mamanguape e Rio Tinto)",
    "area_conhecimento": "Ciências Sociais Aplicadas",
    "area_conhecimento_vestibular": "Área IV - CIÊNCIAS HUMANAS E SOCIAIS",
    "modalidade": "Presencial",
    "unidade_responsavel": "CENTRO DE CIÊNCIAS APLICADAS E EDUCAÇÃO (CCAE)",
    "unidade_coordenacao": "CCAE - COORDENAÇÃO DE ADMINISTRAÇÃO"
  },
  {
    "codigo_inep": "1203263",
    "nome_curso": "ADMINISTRAÇÃO PÚBLICA",
    "grau": "BACHARELADO",
    "turno": "Matutino e Vespertino",
    "campus": "UFPB VIRTUAL",
    "area_conhecimento": "Ciências Sociais Aplicadas",
    "area_conhecimento_vestibular": "Área IV - CIÊNCIAS HUMANAS E SOCIAIS",
    "modalidade": "A Distância",
    "unidade_responsavel": "CENTRO DE TECNOLOGIA E DESENVOLVIMENTO REGIONAL (CTDR)",
    "unidade_coordenacao": "CCSA - COORDENAÇÃO DE ADMINISTRAÇÃO"
  },
  {
    "codigo_inep": "1167933",
    "nome_curso": "AGROECOLOGIA",
    "grau": "BACHARELADO",
    "turno": "Matutino e Vespertino",
    "campus": "Bananeiras",
    "area_conhecimento": "Ciências Agrárias",
    "area_conhecimento_vestibular": "Área I - CIÊNCIAS AGRÁRIAS",
    "modalidade": "Presencial",
    "unidade_responsavel": "CENTRO DE CIÊNCIAS HUMANAS SOCIAIS E AGRÁRIAS (CCHSA)",
    "unidade_coordenacao": "CCHSA - COORDENAÇÃO DE AGROECOLOGIA"
  },
  {
    "codigo_inep": "80589",
    "nome_curso": "AGROINDÚSTRIA",
    "grau": "BACHARELADO",
    "turno": "Matutino e Vespertino",
    "campus": "Bananeiras",
    "area_conhecimento": "Ciências Agrárias",
    "area_conhecimento_vestibular": "Área I - CIÊNCIAS AGRÁRIAS",
    "modalidade": "Presencial",
    "unidade_responsavel": "CENTRO DE CIÊNCIAS HUMANAS SOCIAIS E AGRÁRIAS (CCHSA)",
    "unidade_coordenacao": "CCHSA - COORDENAÇÃO DE AGROINDÚSTRIA"
  },
  {
    "codigo_inep": "13454",
    "nome_curso": "AGRONOMIA",
    "grau": "BACHARELADO",
    "turno": "Matutino e Vespertino",
    "campus": "Areia",
    "area_conhecimento": "Ciências Agrárias",
    "area_conhecimento_vestibular": "Área I - CIÊNCIAS AGRÁRIAS",
    "modalidade": "Presencial",
    "unidade_responsavel": "CENTRO DE CIÊNCIAS AGRÁRIAS (CCA)",
    "unidade_coordenacao": "CCA - COORDENAÇÃO DE AGRONOMIA"
  },
  {
    "codigo_inep": "107348",
    "nome_curso": "ANTROPOLOGIA",
    "grau": "BACHARELADO",
    "turno": "Noturno",
    "campus": "Litoral Norte (Mamanguape e Rio Tinto)",
    "area_conhecimento": "Ciências Sociais Aplicadas",
    "area_conhecimento_vestibular": "Área IV - CIÊNCIAS HUMANAS E SOCIAIS",
    "modalidade": "Presencial",
    "unidade_responsavel": "CENTRO DE CIÊNCIAS APLICADAS E EDUCAÇÃO (CCAE)",
    "unidade_coordenacao": "CCAE - COORDENAÇÃO DE ANTROPOLOGIA E CULTURAS INDÍGENAS"
  },
  {
    "codigo_inep": "13427",
    "nome_curso": "ARQUITETURA E URBANISMO",
    "grau": "BACHARELADO",
    "turno": "Matutino e Vespertino",
    "campus": "João Pessoa",
    "area_conhecimento": "Engenharias",
    "area_conhecimento_vestibular": "Área III - CIÊNCIAS EXATAS E TECNOLÓGICAS",
    "modalidade": "Presencial",
    "unidade_responsavel": "CENTRO DE TECNOLOGIA (CT)",
    "unidade_coordenacao": "CT - COORDENAÇÃO DE ARQUITETURA E URBANISMO"
  },
  {
    "codigo_inep": "113621",
    "nome_curso": "ARQUIVOLOGIA",
    "grau": "BACHARELADO",
    "turno": "Noturno",
    "campus": "João Pessoa",
    "area_conhecimento": "Ciências Sociais Aplicadas",
    "area_conhecimento_vestibular": "Área IV - CIÊNCIAS HUMANAS E SOCIAIS",
    "modalidade": "Presencial",
    "unidade_responsavel": "CENTRO DE CIÊNCIAS SOCIAIS E APLICADAS (CCSA)",
    "unidade_coordenacao": "CCSA - COORDENAÇÃO DE ARQUIVOLOGIA"
  },
  {
    "codigo_inep": "107438",
    "nome_curso": "ARTES VISUAIS",
    "grau": "LICENCIATURA",
    "turno": "Matutino e Vespertino",
    "campus": "João Pessoa",
    "area_conhecimento": "Ciências Humanas",
    "area_conhecimento_vestibular": "Área IV - CIÊNCIAS HUMANAS E SOCIAIS",
    "modalidade": "Presencial",
    "unidade_responsavel": "CENTRO DE COMUNICAÇÃO, TURISMO E ARTES (CCTA)",
    "unidade_coordenacao": "CCTA - COORDENAÇÃO  DE ARTES VISUAIS"
  },
  {
    "codigo_inep": "107440",
    "nome_curso": "ARTES VISUAIS",
    "grau": "BACHARELADO",
    "turno": "Matutino e Vespertino",
    "campus": "João Pessoa",
    "area_conhecimento": "Ciências Humanas",
    "area_conhecimento_vestibular": "Área IV - CIÊNCIAS HUMANAS E SOCIAIS",
    "modalidade": "Presencial",
    "unidade_responsavel": "CENTRO DE COMUNICAÇÃO, TURISMO E ARTES (CCTA)",
    "unidade_coordenacao": "CCTA - COORDENAÇÃO  DE ARTES VISUAIS"
  },
  {
    "codigo_inep": "13396",
    "nome_curso": "BIBLIOTECONOMIA",
    "grau": "BACHARELADO",
    "turno": "Matutino e Vespertino",
    "campus": "João Pessoa",
    "area_conhecimento": "Ciências Sociais Aplicadas",
    "area_conhecimento_vestibular": "Área IV - CIÊNCIAS HUMANAS E SOCIAIS",
    "modalidade": "Presencial",
    "unidade_responsavel": "CENTRO DE CIÊNCIAS SOCIAIS E APLICADAS (CCSA)",
    "unidade_coordenacao": "CCSA - COORDENACÃO DE BIBLIOTECONOMIA E DOCUMENTAÇÃO"
  },
  {
    "codigo_inep": "13396",
    "nome_curso": "BIBLIOTECONOMIA",
    "grau": "BACHARELADO",
    "turno": "Noturno",
    "campus": "João Pessoa",
    "area_conhecimento": "Ciências Sociais Aplicadas",
    "area_conhecimento_vestibular": "Área IV - CIÊNCIAS HUMANAS E SOCIAIS",
    "modalidade": "Presencial",
    "unidade_responsavel": "CENTRO DE CIÊNCIAS SOCIAIS E APLICADAS (CCSA)",
    "unidade_coordenacao": "CCSA - COORDENACÃO DE BIBLIOTECONOMIA E DOCUMENTAÇÃO"
  },
  {
    "codigo_inep": "13396",
    "nome_curso": "BIBLIOTECONOMIA",
    "grau": "BACHARELADO",
    "turno": "Vespertino",
    "campus": "João Pessoa",
    "area_conhecimento": "Ciências Sociais Aplicadas",
    "area_conhecimento_vestibular": "Área IV - CIÊNCIAS HUMANAS E SOCIAIS",
    "modalidade": "Presencial",
    "unidade_responsavel": "CENTRO DE CIÊNCIAS SOCIAIS E APLICADAS (CCSA)",
    "unidade_coordenacao": "CCSA - COORDENACÃO DE BIBLIOTECONOMIA E DOCUMENTAÇÃO"
  },
  {
    "codigo_inep": "1399139",
    "nome_curso": "BIOMEDICINA",
    "grau": "BACHARELADO",
    "turno": "Matutino e Vespertino",
    "campus": "João Pessoa",
    "area_conhecimento": "Ciências da Saúde",
    "area_conhecimento_vestibular": "Área II -CIÊNCIAS BIOLÓGICAS E DA SAÚDE",
    "modalidade": "Presencial",
    "unidade_responsavel": "CENTRO DE CIÊNCIAS DA SAÚDE (CCS)",
    "unidade_coordenacao": "CCS - COORDENAÇÃO DE BIOMEDICINA"
  },
  {
    "codigo_inep": "1189062",
    "nome_curso": "BIOTECNOLOGIA",
    "grau": "BACHARELADO",
    "turno": "Matutino e Vespertino",
    "campus": "João Pessoa",
    "area_conhecimento": "Ciências Exatas e da Terra",
    "area_conhecimento_vestibular": "Área II -CIÊNCIAS BIOLÓGICAS E DA SAÚDE",
    "modalidade": "Presencial",
    "unidade_responsavel": "CENTRO DE BIOTECNOLOGIA",
    "unidade_coordenacao": "CBIOTEC - COORDENAÇÃO DE BIOTECNOLOGIA"
  },
  {
    "codigo_inep": "13401",
    "nome_curso": "CIÊNCIA DA COMPUTAÇÃO",
    "grau": "BACHARELADO",
    "turno": "Matutino e Vespertino",
    "campus": "João Pessoa",
    "area_conhecimento": "Engenharias",
    "area_conhecimento_vestibular": "Área III - CIÊNCIAS EXATAS E TECNOLÓGICAS",
    "modalidade": "Presencial",
    "unidade_responsavel": "CENTRO DE INFORMÁTICA (CI)",
    "unidade_coordenacao": "CI - COORDENAÇÃO DE CIÊNCIAS DA COMPUTAÇÃO (BACHARELADO)"
  },
  {
    "codigo_inep": "98984",
    "nome_curso": "CIÊNCIA DA COMPUTAÇÃO",
    "grau": "LICENCIATURA",
    "turno": "Matutino e Vespertino",
    "campus": "Litoral Norte (Mamanguape e Rio Tinto)",
    "area_conhecimento": "Engenharias",
    "area_conhecimento_vestibular": "Área III - CIÊNCIAS EXATAS E TECNOLÓGICAS",
    "modalidade": "Presencial",
    "unidade_responsavel": "CENTRO DE CIÊNCIAS APLICADAS E EDUCAÇÃO (CCAE)",
    "unidade_coordenacao": "CCAE - COORDENAÇÃO DE CIÊNCIAS DA COMPUTAÇÃO"
  },
  {
    "codigo_inep": "1503759",
    "nome_curso": "CIÊNCIA DE DADOS E INTELIGÊNCIA ARTIFICIAL",
    "grau": "BACHARELADO",
    "turno": "Matutino e Vespertino",
    "campus": "João Pessoa",
    "area_conhecimento": "Engenharias",
    "area_conhecimento_vestibular": "Área III - CIÊNCIAS EXATAS E TECNOLÓGICAS",
    "modalidade": "Presencial",
    "unidade_responsavel": "CENTRO DE INFORMÁTICA (CI)",
    "unidade_coordenacao": "CI - COORDENAÇÃO DE MATEMÁTICA COMPUTACIONAL"
  },
  {
    "codigo_inep": "1564470",
    "nome_curso": "CIÊNCIA DE DADOS PARA NEGÓCIOS",
    "grau": "BACHARELADO",
    "turno": "Vespertino",
    "campus": "João Pessoa",
    "area_conhecimento": "Ciências Sociais Aplicadas",
    "area_conhecimento_vestibular": "Área IV - CIÊNCIAS HUMANAS E SOCIAIS",
    "modalidade": "Presencial",
    "unidade_responsavel": "CENTRO DE CIÊNCIAS SOCIAIS E APLICADAS (CCSA)",
    "unidade_coordenacao": "CCSA - COORDENACÃO DE ECONOMIA"
  },
  {
    "codigo_inep": "13457",
    "nome_curso": "CIÊNCIAS AGRÁRIAS",
    "grau": "LICENCIATURA",
    "turno": "Matutino e Vespertino",
    "campus": "Bananeiras",
    "area_conhecimento": "Ciências Agrárias",
    "area_conhecimento_vestibular": "Área I - CIÊNCIAS AGRÁRIAS",
    "modalidade": "Presencial",
    "unidade_responsavel": "CENTRO DE CIÊNCIAS HUMANAS SOCIAIS E AGRÁRIAS (CCHSA)",
    "unidade_coordenacao": "CCHSA - COORDENAÇÃO DE CIÊNCIAS AGRÁRIAS"
  },
  {
    "codigo_inep": "113701",
    "nome_curso": "CIÊNCIAS AGRÁRIAS -EAD",
    "grau": "LICENCIATURA",
    "turno": "Matutino e Vespertino",
    "campus": "UFPB VIRTUAL",
    "area_conhecimento": "Ciências Agrárias",
    "area_conhecimento_vestibular": "Área I - CIÊNCIAS AGRÁRIAS",
    "modalidade": "A Distância",
    "unidade_responsavel": "CENTRO DE CIÊNCIAS HUMANAS SOCIAIS E AGRÁRIAS (CCHSA)",
    "unidade_coordenacao": "CCHSA - COORDENAÇÃO DE CIÊNCIAS AGRÁRIAS"
  },
  {
    "codigo_inep": "1127039",
    "nome_curso": "CIÊNCIAS ATUARIAIS",
    "grau": "BACHARELADO",
    "turno": "Noturno",
    "campus": "João Pessoa",
    "area_conhecimento": "Ciências Sociais Aplicadas",
    "area_conhecimento_vestibular": "Área IV - CIÊNCIAS HUMANAS E SOCIAIS",
    "modalidade": "Presencial",
    "unidade_responsavel": "CENTRO DE CIÊNCIAS SOCIAIS E APLICADAS (CCSA)",
    "unidade_coordenacao": "CCSA - COORDENAÇÃO DE CIÊNCIAS ATUARIAIS"
  },
  {
    "codigo_inep": "1127039",
    "nome_curso": "CIÊNCIAS ATUARIAIS",
    "grau": "BACHARELADO",
    "turno": "Vespertino",
    "campus": "João Pessoa",
    "area_conhecimento": "Ciências Sociais Aplicadas",
    "area_conhecimento_vestibular": "Área IV - CIÊNCIAS HUMANAS E SOCIAIS",
    "modalidade": "Presencial",
    "unidade_responsavel": "CENTRO DE CIÊNCIAS SOCIAIS E APLICADAS (CCSA)",
    "unidade_coordenacao": "CCSA - COORDENAÇÃO DE CIÊNCIAS ATUARIAIS"
  },
  {
    "codigo_inep": "13399",
    "nome_curso": "CIÊNCIAS BIOLÓGICAS",
    "grau": "LICENCIATURA",
    "turno": "Matutino e Vespertino",
    "campus": "João Pessoa",
    "area_conhecimento": "Ciências Exatas e da Terra",
    "area_conhecimento_vestibular": "Área II -CIÊNCIAS BIOLÓGICAS E DA SAÚDE",
    "modalidade": "Presencial",
    "unidade_responsavel": "CENTRO DE CIÊNCIAS EXATAS E DA NATUREZA (CCEN)",
    "unidade_coordenacao": "CCEN - COORDENAÇÃO DE CIÊNCIAS BIOLÓGICAS (LICENCIATURA)"
  },
  {
    "codigo_inep": "13399",
    "nome_curso": "CIÊNCIAS BIOLÓGICAS",
    "grau": "LICENCIATURA",
    "turno": "Noturno",
    "campus": "João Pessoa",
    "area_conhecimento": "Ciências Exatas e da Terra",
    "area_conhecimento_vestibular": "Área II -CIÊNCIAS BIOLÓGICAS E DA SAÚDE",
    "modalidade": "Presencial",
    "unidade_responsavel": "CENTRO DE CIÊNCIAS EXATAS E DA NATUREZA (CCEN)",
    "unidade_coordenacao": "CCEN - COORDENAÇÃO DE CIÊNCIAS BIOLÓGICAS (LICENCIATURA)"
  },
  {
    "codigo_inep": "313399",
    "nome_curso": "CIÊNCIAS BIOLÓGICAS",
    "grau": "BACHARELADO",
    "turno": "Matutino e Vespertino",
    "campus": "João Pessoa",
    "area_conhecimento": "Ciências Exatas e da Terra",
    "area_conhecimento_vestibular": "Área II -CIÊNCIAS BIOLÓGICAS E DA SAÚDE",
    "modalidade": "Presencial",
    "unidade_responsavel": "CENTRO DE CIÊNCIAS EXATAS E DA NATUREZA (CCEN)",
    "unidade_coordenacao": "CCEN - COORDENAÇÃO DE CIÊNCIAS BIOLÓGICAS (BACHARELADO)"
  },
  {
    "codigo_inep": "397767",
    "nome_curso": "CIÊNCIAS BIOLÓGICAS",
    "grau": "BACHARELADO",
    "turno": "Matutino e Vespertino",
    "campus": "Areia",
    "area_conhecimento": "Ciências Exatas e da Terra",
    "area_conhecimento_vestibular": "Área III - CIÊNCIAS EXATAS E TECNOLÓGICAS",
    "modalidade": "Presencial",
    "unidade_responsavel": "CENTRO DE CIÊNCIAS AGRÁRIAS (CCA)",
    "unidade_coordenacao": "CCA - COORDENAÇÃO DE CIÊNCIAS BIOLÓGICAS"
  },
  {
    "codigo_inep": "397767",
    "nome_curso": "CIÊNCIAS BIOLÓGICAS",
    "grau": "LICENCIATURA CURTA",
    "turno": "Matutino e Vespertino",
    "campus": "Areia",
    "area_conhecimento": "Ciências Exatas e da Terra",
    "area_conhecimento_vestibular": "Área III - CIÊNCIAS EXATAS E TECNOLÓGICAS",
    "modalidade": "Presencial",
    "unidade_responsavel": "CENTRO DE CIÊNCIAS AGRÁRIAS (CCA)",
    "unidade_coordenacao": "CCA - COORDENAÇÃO DE CIÊNCIAS BIOLÓGICAS"
  },
  {
    "codigo_inep": "97767",
    "nome_curso": "CIÊNCIAS BIOLÓGICAS",
    "grau": "LICENCIATURA",
    "turno": "Matutino e Vespertino",
    "campus": "Areia",
    "area_conhecimento": "Ciências Exatas e da Terra",
    "area_conhecimento_vestibular": "Área III - CIÊNCIAS EXATAS E TECNOLÓGICAS",
    "modalidade": "Presencial",
    "unidade_responsavel": "CENTRO DE CIÊNCIAS AGRÁRIAS (CCA)",
    "unidade_coordenacao": "CCA - COORDENAÇÃO DE CIÊNCIAS BIOLÓGICAS"
  },
  {
    "codigo_inep": "113699",
    "nome_curso": "CIÊNCIAS BIOLÓGICAS - EAD",
    "grau": "LICENCIATURA",
    "turno": "Matutino e Vespertino",
    "campus": "UFPB VIRTUAL",
    "area_conhecimento": "Ciências Exatas e da Terra",
    "area_conhecimento_vestibular": "Área III - CIÊNCIAS EXATAS E TECNOLÓGICAS",
    "modalidade": "A Distância",
    "unidade_responsavel": "CENTRO DE CIÊNCIAS EXATAS E DA NATUREZA (CCEN)",
    "unidade_coordenacao": "CCEN - COORDENAÇÃO DE CIÊNCIAS BIOLÓGICAS (EAD)"
  },
  {
    "codigo_inep": "13397",
    "nome_curso": "CIÊNCIAS CONTÁBEIS",
    "grau": "BACHARELADO",
    "turno": "Matutino e Vespertino",
    "campus": "João Pessoa",
    "area_conhecimento": "Ciências Sociais Aplicadas",
    "area_conhecimento_vestibular": "Área IV - CIÊNCIAS HUMANAS E SOCIAIS",
    "modalidade": "Presencial",
    "unidade_responsavel": "CENTRO DE CIÊNCIAS SOCIAIS E APLICADAS (CCSA)",
    "unidade_coordenacao": "CCSA - COORDENACÃO DE CIÊNCIAS CONTÁBEIS"
  },
  {
    "codigo_inep": "13397",
    "nome_curso": "CIÊNCIAS CONTÁBEIS",
    "grau": "BACHARELADO",
    "turno": "Noturno",
    "campus": "João Pessoa",
    "area_conhecimento": "Ciências Sociais Aplicadas",
    "area_conhecimento_vestibular": "Área IV - CIÊNCIAS HUMANAS E SOCIAIS",
    "modalidade": "Presencial",
    "unidade_responsavel": "CENTRO DE CIÊNCIAS SOCIAIS E APLICADAS (CCSA)",
    "unidade_coordenacao": "CCSA - COORDENACÃO DE CIÊNCIAS CONTÁBEIS"
  },
  {
    "codigo_inep": "98976",
    "nome_curso": "CIÊNCIAS CONTÁBEIS",
    "grau": "BACHARELADO",
    "turno": "Noturno",
    "campus": "Litoral Norte (Mamanguape e Rio Tinto)",
    "area_conhecimento": "Ciências Sociais Aplicadas",
    "area_conhecimento_vestibular": "Área IV - CIÊNCIAS HUMANAS E SOCIAIS",
    "modalidade": "Presencial",
    "unidade_responsavel": "CENTRO DE CIÊNCIAS APLICADAS E EDUCAÇÃO (CCAE)",
    "unidade_coordenacao": "CCAE - COORDENAÇÃO DE CIÊNCIAS CONTÁBEIS"
  },
  {
    "codigo_inep": "1162838",
    "nome_curso": "CIÊNCIAS DAS RELIGIÕES",
    "grau": "BACHARELADO",
    "turno": "Noturno",
    "campus": "João Pessoa",
    "area_conhecimento": "Ciências Humanas",
    "area_conhecimento_vestibular": "Área IV - CIÊNCIAS HUMANAS E SOCIAIS",
    "modalidade": "Presencial",
    "unidade_responsavel": "CENTRO DE EDUCAÇÃO (CE)",
    "unidade_coordenacao": "CE - COORDENAÇÃO DE CIÊNCIAS DAS RELIGIÕES"
  },
  {
    "codigo_inep": "116826",
    "nome_curso": "CIÊNCIAS DAS RELIGIÕES",
    "grau": "LICENCIATURA",
    "turno": "Noturno",
    "campus": "João Pessoa",
    "area_conhecimento": "Ciências Humanas",
    "area_conhecimento_vestibular": "Área IV - CIÊNCIAS HUMANAS E SOCIAIS",
    "modalidade": "Presencial",
    "unidade_responsavel": "CENTRO DE EDUCAÇÃO (CE)",
    "unidade_coordenacao": "CE - COORDENAÇÃO DE CIÊNCIAS DAS RELIGIÕES"
  },
  {
    "codigo_inep": "116826",
    "nome_curso": "CIÊNCIAS DAS RELIGIÕES",
    "grau": "LICENCIATURA",
    "turno": "Vespertino",
    "campus": "João Pessoa",
    "area_conhecimento": "Ciências Humanas",
    "area_conhecimento_vestibular": "Área IV - CIÊNCIAS HUMANAS E SOCIAIS",
    "modalidade": "Presencial",
    "unidade_responsavel": "CENTRO DE EDUCAÇÃO (CE)",
    "unidade_coordenacao": "CE - COORDENAÇÃO DE CIÊNCIAS DAS RELIGIÕES"
  },
  {
    "codigo_inep": "13394",
    "nome_curso": "CIÊNCIAS ECONÔMICAS",
    "grau": "BACHARELADO",
    "turno": "Matutino e Vespertino",
    "campus": "João Pessoa",
    "area_conhecimento": "Ciências Sociais Aplicadas",
    "area_conhecimento_vestibular": "Área IV - CIÊNCIAS HUMANAS E SOCIAIS",
    "modalidade": "Presencial",
    "unidade_responsavel": "CENTRO DE CIÊNCIAS SOCIAIS E APLICADAS (CCSA)",
    "unidade_coordenacao": "CCSA - COORDENACÃO DE ECONOMIA"
  },
  {
    "codigo_inep": "13394",
    "nome_curso": "CIÊNCIAS ECONÔMICAS",
    "grau": "BACHARELADO",
    "turno": "Noturno",
    "campus": "João Pessoa",
    "area_conhecimento": "Ciências Sociais Aplicadas",
    "area_conhecimento_vestibular": "Área IV - CIÊNCIAS HUMANAS E SOCIAIS",
    "modalidade": "Presencial",
    "unidade_responsavel": "CENTRO DE CIÊNCIAS SOCIAIS E APLICADAS (CCSA)",
    "unidade_coordenacao": "CCSA - COORDENACÃO DE ECONOMIA"
  },
  {
    "codigo_inep": "113705",
    "nome_curso": "CIÊNCIAS NATURAIS",
    "grau": "LICENCIATURA",
    "turno": "Matutino e Vespertino",
    "campus": "UFPB VIRTUAL",
    "area_conhecimento": "Ciências Exatas e da Terra",
    "area_conhecimento_vestibular": "Área III - CIÊNCIAS EXATAS E TECNOLÓGICAS",
    "modalidade": "A Distância",
    "unidade_responsavel": "CENTRO DE EDUCAÇÃO (CE)",
    "unidade_coordenacao": "CE - COORDENAÇÃO EM CIÊNCIAS NATURAIS (EAD)"
  },
  {
    "codigo_inep": "1110230",
    "nome_curso": "CIÊNCIAS SOCIAIS",
    "grau": "LICENCIATURA",
    "turno": "Noturno",
    "campus": "João Pessoa",
    "area_conhecimento": "Ciências Sociais Aplicadas",
    "area_conhecimento_vestibular": "Área IV - CIÊNCIAS HUMANAS E SOCIAIS",
    "modalidade": "Presencial",
    "unidade_responsavel": "CENTRO DE CIÊNCIAS HUMANAS, LETRAS E ARTES (CCHLA)",
    "unidade_coordenacao": "CCHLA - COORDENAÇÃO DE CIÊNCIAS SOCIAIS"
  },
  {
    "codigo_inep": "13459",
    "nome_curso": "CIÊNCIAS SOCIAIS",
    "grau": "BACHARELADO",
    "turno": "Matutino e Vespertino",
    "campus": "João Pessoa",
    "area_conhecimento": "Ciências Sociais Aplicadas",
    "area_conhecimento_vestibular": "Área IV - CIÊNCIAS HUMANAS E SOCIAIS",
    "modalidade": "Presencial",
    "unidade_responsavel": "CENTRO DE CIÊNCIAS HUMANAS, LETRAS E ARTES (CCHLA)",
    "unidade_coordenacao": "CCHLA - COORDENAÇÃO DE CIÊNCIAS SOCIAIS"
  },
  {
    "codigo_inep": "1166771",
    "nome_curso": "CINEMA E AUDIOVISUAL",
    "grau": "BACHARELADO",
    "turno": "Matutino e Vespertino",
    "campus": "João Pessoa",
    "area_conhecimento": "Ciências Humanas",
    "area_conhecimento_vestibular": "Área IV - CIÊNCIAS HUMANAS E SOCIAIS",
    "modalidade": "Presencial",
    "unidade_responsavel": "CENTRO DE COMUNICAÇÃO, TURISMO E ARTES (CCTA)",
    "unidade_coordenacao": "CCTA - COORDENAÇÃO DE CINEMA E AUDIOVISUAL"
  },
  {
    "codigo_inep": "1203266",
    "nome_curso": "COMPUTAÇÃO",
    "grau": "LICENCIATURA",
    "turno": "Matutino e Vespertino",
    "campus": "UFPB VIRTUAL",
    "area_conhecimento": "Ciências Exatas e da Terra",
    "area_conhecimento_vestibular": "Área III - CIÊNCIAS EXATAS E TECNOLÓGICAS",
    "modalidade": "A Distância",
    "unidade_responsavel": "CENTRO DE INFORMÁTICA (CI)",
    "unidade_coordenacao": "CI - COORDENAÇÃO DE COMPUTAÇÃO (LICENCIATURA - EAD)"
  },
  {
    "codigo_inep": "1125641",
    "nome_curso": "COMUNICAÇÃO EM MÍDIAS DIGITAIS",
    "grau": "BACHARELADO",
    "turno": "Vespertino",
    "campus": "João Pessoa",
    "area_conhecimento": "Ciências Humanas",
    "area_conhecimento_vestibular": "Área IV - CIÊNCIAS HUMANAS E SOCIAIS",
    "modalidade": "Presencial",
    "unidade_responsavel": "CENTRO DE CIÊNCIAS HUMANAS, LETRAS E ARTES (CCHLA)",
    "unidade_coordenacao": "CCHLA - COORDENAÇÃO DE COMUNICAÇÃO EM MÍDIAS DIGITAIS"
  },
  {
    "codigo_inep": "22457",
    "nome_curso": "COMUNICAÇÃO SOCIAL",
    "grau": "BACHARELADO",
    "turno": "Matutino e Vespertino",
    "campus": "João Pessoa",
    "area_conhecimento": "Ciências Sociais Aplicadas",
    "area_conhecimento_vestibular": "Área IV - CIÊNCIAS HUMANAS E SOCIAIS",
    "modalidade": "Presencial",
    "unidade_responsavel": "CENTRO DE COMUNICAÇÃO, TURISMO E ARTES (CCTA)",
    "unidade_coordenacao": "CCTA - COORDENAÇÃO DE RADIALISMO"
  },
  {
    "codigo_inep": "28408",
    "nome_curso": "COMUNICAÇÃO SOCIAL",
    "grau": "BACHARELADO",
    "turno": "Noturno",
    "campus": "João Pessoa",
    "area_conhecimento": "Ciências Sociais Aplicadas",
    "area_conhecimento_vestibular": "Área IV - CIÊNCIAS HUMANAS E SOCIAIS",
    "modalidade": "Presencial",
    "unidade_responsavel": "CENTRO DE COMUNICAÇÃO, TURISMO E ARTES (CCTA)",
    "unidade_coordenacao": "CCTA - COORDENAÇÃO DE RADIALISMO"
  },
  {
    "codigo_inep": "30652",
    "nome_curso": "COMUNICAÇÃO SOCIAL",
    "grau": "BACHARELADO",
    "turno": "Matutino e Vespertino",
    "campus": "João Pessoa",
    "area_conhecimento": "Ciências Sociais Aplicadas",
    "area_conhecimento_vestibular": "Área IV - CIÊNCIAS HUMANAS E SOCIAIS",
    "modalidade": "Presencial",
    "unidade_responsavel": "CENTRO DE COMUNICAÇÃO, TURISMO E ARTES (CCTA)",
    "unidade_coordenacao": "CCTA - COORDENAÇÃO DE RADIALISMO"
  },
  {
    "codigo_inep": "1191007",
    "nome_curso": "DANÇA",
    "grau": "LICENCIATURA",
    "turno": "Matutino e Vespertino",
    "campus": "João Pessoa",
    "area_conhecimento": "Ciências Humanas",
    "area_conhecimento_vestibular": "Área IV - CIÊNCIAS HUMANAS E SOCIAIS",
    "modalidade": "Presencial",
    "unidade_responsavel": "CENTRO DE COMUNICAÇÃO, TURISMO E ARTES (CCTA)",
    "unidade_coordenacao": "CCTA - COORDENAÇÃO DE DANÇA (LICENCIATURA)"
  },
  {
    "codigo_inep": "107352",
    "nome_curso": "DESIGN",
    "grau": "BACHARELADO",
    "turno": "Matutino e Vespertino",
    "campus": "Litoral Norte (Mamanguape e Rio Tinto)",
    "area_conhecimento": "Engenharias",
    "area_conhecimento_vestibular": "Área III - CIÊNCIAS EXATAS E TECNOLÓGICAS",
    "modalidade": "Presencial",
    "unidade_responsavel": "CENTRO DE CIÊNCIAS APLICADAS E EDUCAÇÃO (CCAE)",
    "unidade_coordenacao": "CCAE - COORDENAÇÃO DE DESIGN"
  },
  {
    "codigo_inep": "1110415",
    "nome_curso": "DIREITO",
    "grau": "BACHARELADO",
    "turno": "Matutino e Vespertino",
    "campus": "João Pessoa",
    "area_conhecimento": "Ciências Sociais Aplicadas",
    "area_conhecimento_vestibular": "Área IV - CIÊNCIAS HUMANAS E SOCIAIS",
    "modalidade": "Presencial",
    "unidade_responsavel": "CENTRO DE CIÊNCIAS JURÍDICAS (CCJ)",
    "unidade_coordenacao": "CCJ - COORDENAÇÃO DE DIREITO (SANTA RITA)"
  },
  {
    "codigo_inep": "1110415",
    "nome_curso": "DIREITO",
    "grau": "BACHARELADO",
    "turno": "Noturno",
    "campus": "João Pessoa",
    "area_conhecimento": "Ciências Sociais Aplicadas",
    "area_conhecimento_vestibular": "Área IV - CIÊNCIAS HUMANAS E SOCIAIS",
    "modalidade": "Presencial",
    "unidade_responsavel": "CENTRO DE CIÊNCIAS JURÍDICAS (CCJ)",
    "unidade_coordenacao": "CCJ - COORDENAÇÃO DE DIREITO (SANTA RITA)"
  },
  {
    "codigo_inep": "13398",
    "nome_curso": "DIREITO",
    "grau": "BACHARELADO",
    "turno": "Matutino e Vespertino",
    "campus": "João Pessoa",
    "area_conhecimento": "Ciências Sociais Aplicadas",
    "area_conhecimento_vestibular": "Área IV - CIÊNCIAS HUMANAS E SOCIAIS",
    "modalidade": "Presencial",
    "unidade_responsavel": "CENTRO DE CIÊNCIAS JURÍDICAS (CCJ)",
    "unidade_coordenacao": "CCJ - COORDENAÇÃO DE DIREITO (JOÃO PESSOA)"
  },
  {
    "codigo_inep": "13398",
    "nome_curso": "DIREITO",
    "grau": "BACHARELADO",
    "turno": "Noturno",
    "campus": "João Pessoa",
    "area_conhecimento": "Ciências Sociais Aplicadas",
    "area_conhecimento_vestibular": "Área IV - CIÊNCIAS HUMANAS E SOCIAIS",
    "modalidade": "Presencial",
    "unidade_responsavel": "CENTRO DE CIÊNCIAS JURÍDICAS (CCJ)",
    "unidade_coordenacao": "CCJ - COORDENAÇÃO DE DIREITO (JOÃO PESSOA)"
  },
  {
    "codigo_inep": "13398",
    "nome_curso": "DIREITO",
    "grau": "BACHARELADO",
    "turno": "Vespertino",
    "campus": "João Pessoa",
    "area_conhecimento": "Ciências Sociais Aplicadas",
    "area_conhecimento_vestibular": "Área IV - CIÊNCIAS HUMANAS E SOCIAIS",
    "modalidade": "Presencial",
    "unidade_responsavel": "CENTRO DE CIÊNCIAS JURÍDICAS (CCJ)",
    "unidade_coordenacao": "CCJ - COORDENAÇÃO DE DIREITO (JOÃO PESSOA)"
  },
  {
    "codigo_inep": "98980",
    "nome_curso": "ECOLOGIA",
    "grau": "BACHARELADO",
    "turno": "Matutino e Vespertino",
    "campus": "Litoral Norte (Mamanguape e Rio Tinto)",
    "area_conhecimento": "Ciências Exatas e da Terra",
    "area_conhecimento_vestibular": "Área II -CIÊNCIAS BIOLÓGICAS E DA SAÚDE",
    "modalidade": "Presencial",
    "unidade_responsavel": "CENTRO DE CIÊNCIAS APLICADAS E EDUCAÇÃO (CCAE)",
    "unidade_coordenacao": "CCAE - COORDENAÇÃO DE ECOLOGIA"
  },
  {
    "codigo_inep": "122288",
    "nome_curso": "EDUCAÇÃO FÍSICA",
    "grau": "BACHARELADO",
    "turno": "Matutino e Vespertino",
    "campus": "João Pessoa",
    "area_conhecimento": "Ciências da Saúde",
    "area_conhecimento_vestibular": "Área II -CIÊNCIAS BIOLÓGICAS E DA SAÚDE",
    "modalidade": "Presencial",
    "unidade_responsavel": "CENTRO DE CIÊNCIAS DA SAÚDE (CCS)",
    "unidade_coordenacao": "CCS - COORDENAÇÃO DE EDUCAÇÃO FÍSICA (BACHARELADO)"
  },
  {
    "codigo_inep": "13423",
    "nome_curso": "EDUCAÇÃO FÍSICA - LICENCIATURA",
    "grau": "LICENCIATURA",
    "turno": "Matutino e Vespertino",
    "campus": "João Pessoa",
    "area_conhecimento": "Ciências da Saúde",
    "area_conhecimento_vestibular": "Área II -CIÊNCIAS BIOLÓGICAS E DA SAÚDE",
    "modalidade": "Presencial",
    "unidade_responsavel": "CENTRO DE CIÊNCIAS DA SAÚDE (CCS)",
    "unidade_coordenacao": "CCS - COORDENAÇÃO DE EDUCAÇÃO FÍSICA (LICENCIATURA)"
  },
  {
    "codigo_inep": "44257",
    "nome_curso": "ENFERMAGEM",
    "grau": "LICENCIATURA",
    "turno": "Matutino e Vespertino",
    "campus": "João Pessoa",
    "area_conhecimento": "Ciências da Saúde",
    "area_conhecimento_vestibular": "Área II -CIÊNCIAS BIOLÓGICAS E DA SAÚDE",
    "modalidade": "Presencial",
    "unidade_responsavel": "CENTRO DE CIÊNCIAS DA SAÚDE (CCS)",
    "unidade_coordenacao": "CCS - COORDENAÇÃO DE ENFERMAGEM"
  },
  {
    "codigo_inep": "44258",
    "nome_curso": "ENFERMAGEM",
    "grau": "BACHARELADO",
    "turno": "Matutino e Vespertino",
    "campus": "João Pessoa",
    "area_conhecimento": "Ciências da Saúde",
    "area_conhecimento_vestibular": "Área II -CIÊNCIAS BIOLÓGICAS E DA SAÚDE",
    "modalidade": "Presencial",
    "unidade_responsavel": "CENTRO DE CIÊNCIAS DA SAÚDE (CCS)",
    "unidade_coordenacao": "CCS - COORDENAÇÃO DE ENFERMAGEM"
  },
  {
    "codigo_inep": "44258",
    "nome_curso": "ENFERMAGEM",
    "grau": "LICENCIATURA E BACHARELADO",
    "turno": "Matutino e Vespertino",
    "campus": "João Pessoa",
    "area_conhecimento": "Ciências da Saúde",
    "area_conhecimento_vestibular": "Área II -CIÊNCIAS BIOLÓGICAS E DA SAÚDE",
    "modalidade": "Presencial",
    "unidade_responsavel": "CENTRO DE CIÊNCIAS DA SAÚDE (CCS)",
    "unidade_coordenacao": "CCS - COORDENAÇÃO DE ENFERMAGEM"
  },
  {
    "codigo_inep": "113615",
    "nome_curso": "ENGENHARIA AMBIENTAL",
    "grau": "BACHARELADO",
    "turno": "Matutino e Vespertino",
    "campus": "João Pessoa",
    "area_conhecimento": "Engenharias",
    "area_conhecimento_vestibular": "Área III - CIÊNCIAS EXATAS E TECNOLÓGICAS",
    "modalidade": "Presencial",
    "unidade_responsavel": "CENTRO DE TECNOLOGIA (CT)",
    "unidade_coordenacao": "CT - COORDENAÇÃO DE ENGENHARIA AMBIENTAL"
  },
  {
    "codigo_inep": "13429",
    "nome_curso": "ENGENHARIA CIVIL",
    "grau": "BACHARELADO",
    "turno": "Matutino e Vespertino",
    "campus": "João Pessoa",
    "area_conhecimento": "Engenharias",
    "area_conhecimento_vestibular": "Área III - CIÊNCIAS EXATAS E TECNOLÓGICAS",
    "modalidade": "Presencial",
    "unidade_responsavel": "CENTRO DE TECNOLOGIA (CT)",
    "unidade_coordenacao": "CT - COORDENAÇÃO DE ENGENHARIA CIVIL"
  },
  {
    "codigo_inep": "1127164",
    "nome_curso": "ENGENHARIA DA COMPUTAÇÃO",
    "grau": "BACHARELADO",
    "turno": "Matutino e Vespertino",
    "campus": "João Pessoa",
    "area_conhecimento": "Engenharias",
    "area_conhecimento_vestibular": "Área III - CIÊNCIAS EXATAS E TECNOLÓGICAS",
    "modalidade": "Presencial",
    "unidade_responsavel": "CENTRO DE INFORMÁTICA (CI)",
    "unidade_coordenacao": "CI - COORDENAÇÃO DE ENGENHARIA COMPUTACIONAL"
  },
  {
    "codigo_inep": "13428",
    "nome_curso": "ENGENHARIA DE ALIMENTOS",
    "grau": "BACHARELADO",
    "turno": "Matutino e Vespertino",
    "campus": "João Pessoa",
    "area_conhecimento": "Engenharias",
    "area_conhecimento_vestibular": "Área III - CIÊNCIAS EXATAS E TECNOLÓGICAS",
    "modalidade": "Presencial",
    "unidade_responsavel": "CENTRO DE TECNOLOGIA (CT)",
    "unidade_coordenacao": "CT - COORDENAÇÃO DE ENGENHARIA DE ALIMENTOS"
  },
  {
    "codigo_inep": "1189063",
    "nome_curso": "ENGENHARIA DE ENERGIAS RENOVÁVEIS",
    "grau": "BACHARELADO",
    "turno": "Matutino e Vespertino",
    "campus": "João Pessoa",
    "area_conhecimento": "Engenharias",
    "area_conhecimento_vestibular": "Área III - CIÊNCIAS EXATAS E TECNOLÓGICAS",
    "modalidade": "Presencial",
    "unidade_responsavel": "CENTRO DE ENERGIAS E ALTERNATIVAS E RENOVÁVEIS (CEAR)",
    "unidade_coordenacao": "CEAR - COORDENAÇÃO DE ENGENHARIA DE ENERGIAS RENOVÁVEIS"
  },
  {
    "codigo_inep": "113617",
    "nome_curso": "ENGENHARIA DE MATERIAIS",
    "grau": "BACHARELADO",
    "turno": "Matutino e Vespertino",
    "campus": "João Pessoa",
    "area_conhecimento": "Engenharias",
    "area_conhecimento_vestibular": "Área III - CIÊNCIAS EXATAS E TECNOLÓGICAS",
    "modalidade": "Presencial",
    "unidade_responsavel": "CENTRO DE TECNOLOGIA (CT)",
    "unidade_coordenacao": "CT - COORDENAÇÃO DE ENGENHARIA DE MATERIAIS"
  },
  {
    "codigo_inep": "122934",
    "nome_curso": "ENGENHARIA DE PRODUÇÃO",
    "grau": "BACHARELADO",
    "turno": "Noturno",
    "campus": "João Pessoa",
    "area_conhecimento": "Engenharias",
    "area_conhecimento_vestibular": "Área III - CIÊNCIAS EXATAS E TECNOLÓGICAS",
    "modalidade": "Presencial",
    "unidade_responsavel": "CENTRO DE TECNOLOGIA (CT)",
    "unidade_coordenacao": "CT - COORDENAÇÃO DE ENGENHARIA DE PRODUÇÃO"
  },
  {
    "codigo_inep": "19563",
    "nome_curso": "ENGENHARIA DE PRODUÇÃO MECÂNICA",
    "grau": "BACHARELADO",
    "turno": "Matutino e Vespertino",
    "campus": "João Pessoa",
    "area_conhecimento": "Engenharias",
    "area_conhecimento_vestibular": "Área III - CIÊNCIAS EXATAS E TECNOLÓGICAS",
    "modalidade": "Presencial",
    "unidade_responsavel": "CENTRO DE TECNOLOGIA (CT)",
    "unidade_coordenacao": "CT - COORDENAÇÃO DE ENGENHARIA DE PRODUÇÃO MECÂNICA"
  },
  {
    "codigo_inep": "113609",
    "nome_curso": "ENGENHARIA ELÉTRICA",
    "grau": "BACHARELADO",
    "turno": "Matutino e Vespertino",
    "campus": "João Pessoa",
    "area_conhecimento": "Engenharias",
    "area_conhecimento_vestibular": "Área III - CIÊNCIAS EXATAS E TECNOLÓGICAS",
    "modalidade": "Presencial",
    "unidade_responsavel": "CENTRO DE ENERGIAS E ALTERNATIVAS E RENOVÁVEIS (CEAR)",
    "unidade_coordenacao": "CEAR - COORDENAÇÃO DE ENGENHARIA ELÉTRICA"
  },
  {
    "codigo_inep": "13430",
    "nome_curso": "ENGENHARIA MECÂNICA",
    "grau": "BACHARELADO",
    "turno": "Matutino e Vespertino",
    "campus": "João Pessoa",
    "area_conhecimento": "Engenharias",
    "area_conhecimento_vestibular": "Área III - CIÊNCIAS EXATAS E TECNOLÓGICAS",
    "modalidade": "Presencial",
    "unidade_responsavel": "CENTRO DE TECNOLOGIA (CT)",
    "unidade_coordenacao": "CT - COORDENAÇÃO DE ENGENHARIA MECÂNICA"
  },
  {
    "codigo_inep": "113604",
    "nome_curso": "ENGENHARIA QUÍMICA",
    "grau": "BACHARELADO",
    "turno": "Matutino e Vespertino",
    "campus": "João Pessoa",
    "area_conhecimento": "Engenharias",
    "area_conhecimento_vestibular": "Área III - CIÊNCIAS EXATAS E TECNOLÓGICAS",
    "modalidade": "Presencial",
    "unidade_responsavel": "CENTRO DE TECNOLOGIA (CT)",
    "unidade_coordenacao": "CT - COORDENAÇÃO DE ENGENHARIA QUÍMICA"
  },
  {
    "codigo_inep": "43454",
    "nome_curso": "ESTATÍSTICA",
    "grau": "BACHARELADO",
    "turno": "Matutino e Vespertino",
    "campus": "João Pessoa",
    "area_conhecimento": "Ciências Exatas e da Terra",
    "area_conhecimento_vestibular": "Área III - CIÊNCIAS EXATAS E TECNOLÓGICAS",
    "modalidade": "Presencial",
    "unidade_responsavel": "CENTRO DE CIÊNCIAS EXATAS E DA NATUREZA (CCEN)",
    "unidade_coordenacao": "CCEN - COORDENAÇÃO DE ESTATÍSTICA"
  },
  {
    "codigo_inep": "13421",
    "nome_curso": "FARMÁCIA",
    "grau": "BACHARELADO",
    "turno": "Matutino e Vespertino",
    "campus": "João Pessoa",
    "area_conhecimento": "Ciências da Saúde",
    "area_conhecimento_vestibular": "Área II -CIÊNCIAS BIOLÓGICAS E DA SAÚDE",
    "modalidade": "Presencial",
    "unidade_responsavel": "CENTRO DE CIÊNCIAS DA SAÚDE (CCS)",
    "unidade_coordenacao": "CCS - COORDENAÇÃO DE FARMÁCIA"
  },
  {
    "codigo_inep": "13421",
    "nome_curso": "FARMÁCIA",
    "grau": "OUTRO TIPO DE GRAU ACADÊMICO",
    "turno": "Matutino e Vespertino",
    "campus": "João Pessoa",
    "area_conhecimento": "Ciências da Saúde",
    "area_conhecimento_vestibular": "Área II -CIÊNCIAS BIOLÓGICAS E DA SAÚDE",
    "modalidade": "Presencial",
    "unidade_responsavel": "CENTRO DE CIÊNCIAS DA SAÚDE (CCS)",
    "unidade_coordenacao": "CCS - COORDENAÇÃO DE FARMÁCIA"
  },
  {
    "codigo_inep": "13409",
    "nome_curso": "FILOSOFIA",
    "grau": "LICENCIATURA",
    "turno": "Noturno",
    "campus": "João Pessoa",
    "area_conhecimento": "Ciências Humanas",
    "area_conhecimento_vestibular": "Área IV - CIÊNCIAS HUMANAS E SOCIAIS",
    "modalidade": "Presencial",
    "unidade_responsavel": "CENTRO DE CIÊNCIAS HUMANAS, LETRAS E ARTES (CCHLA)",
    "unidade_coordenacao": "CCHLA - COORDENAÇÃO DE FILOSOFIA"
  },
  {
    "codigo_inep": "313409",
    "nome_curso": "FILOSOFIA",
    "grau": "BACHARELADO",
    "turno": "Noturno",
    "campus": "João Pessoa",
    "area_conhecimento": "Ciências Humanas",
    "area_conhecimento_vestibular": "Área IV - CIÊNCIAS HUMANAS E SOCIAIS",
    "modalidade": "Presencial",
    "unidade_responsavel": "CENTRO DE CIÊNCIAS HUMANAS, LETRAS E ARTES (CCHLA)",
    "unidade_coordenacao": "CCHLA - COORDENAÇÃO DE FILOSOFIA"
  },
  {
    "codigo_inep": "13400",
    "nome_curso": "FÍSICA",
    "grau": "LICENCIATURA",
    "turno": "Matutino e Vespertino",
    "campus": "João Pessoa",
    "area_conhecimento": "Ciências Exatas e da Terra",
    "area_conhecimento_vestibular": "Área III - CIÊNCIAS EXATAS E TECNOLÓGICAS",
    "modalidade": "Presencial",
    "unidade_responsavel": "CENTRO DE CIÊNCIAS EXATAS E DA NATUREZA (CCEN)",
    "unidade_coordenacao": "CCEN - COORDENAÇÃO DE FÍSICA"
  },
  {
    "codigo_inep": "13400",
    "nome_curso": "FÍSICA",
    "grau": "LICENCIATURA",
    "turno": "Noturno",
    "campus": "João Pessoa",
    "area_conhecimento": "Ciências Exatas e da Terra",
    "area_conhecimento_vestibular": "Área III - CIÊNCIAS EXATAS E TECNOLÓGICAS",
    "modalidade": "Presencial",
    "unidade_responsavel": "CENTRO DE CIÊNCIAS EXATAS E DA NATUREZA (CCEN)",
    "unidade_coordenacao": "CCEN - COORDENAÇÃO DE FÍSICA"
  },
  {
    "codigo_inep": "313400",
    "nome_curso": "FÍSICA",
    "grau": "BACHARELADO",
    "turno": "Matutino e Vespertino",
    "campus": "João Pessoa",
    "area_conhecimento": "Ciências Exatas e da Terra",
    "area_conhecimento_vestibular": "Área III - CIÊNCIAS EXATAS E TECNOLÓGICAS",
    "modalidade": "Presencial",
    "unidade_responsavel": "CENTRO DE CIÊNCIAS EXATAS E DA NATUREZA (CCEN)",
    "unidade_coordenacao": "CCEN - COORDENAÇÃO DE FÍSICA"
  },
  {
    "codigo_inep": "313400",
    "nome_curso": "FÍSICA",
    "grau": "BACHARELADO",
    "turno": "Noturno",
    "campus": "João Pessoa",
    "area_conhecimento": "Ciências Exatas e da Terra",
    "area_conhecimento_vestibular": "Área III - CIÊNCIAS EXATAS E TECNOLÓGICAS",
    "modalidade": "Presencial",
    "unidade_responsavel": "CENTRO DE CIÊNCIAS EXATAS E DA NATUREZA (CCEN)",
    "unidade_coordenacao": "CCEN - COORDENAÇÃO DE FÍSICA"
  },
  {
    "codigo_inep": "13422",
    "nome_curso": "FISIOTERAPIA",
    "grau": "BACHARELADO",
    "turno": "Matutino e Vespertino",
    "campus": "João Pessoa",
    "area_conhecimento": "Ciências da Saúde",
    "area_conhecimento_vestibular": "Área II -CIÊNCIAS BIOLÓGICAS E DA SAÚDE",
    "modalidade": "Presencial",
    "unidade_responsavel": "CENTRO DE CIÊNCIAS DA SAÚDE (CCS)",
    "unidade_coordenacao": "CCS - COORDENAÇÃO DE FISIOTERAPIA"
  },
  {
    "codigo_inep": "122918",
    "nome_curso": "FONOAUDIOLOGIA",
    "grau": "BACHARELADO",
    "turno": "Matutino e Vespertino",
    "campus": "João Pessoa",
    "area_conhecimento": "Ciências da Saúde",
    "area_conhecimento_vestibular": "Área II -CIÊNCIAS BIOLÓGICAS E DA SAÚDE",
    "modalidade": "Presencial",
    "unidade_responsavel": "CENTRO DE CIÊNCIAS DA SAÚDE (CCS)",
    "unidade_coordenacao": "CCS - COORDENAÇÃO DE FONOAUDIOLOGIA"
  },
  {
    "codigo_inep": "5001240",
    "nome_curso": "GASTRONOMIA",
    "grau": "BACHARELADO",
    "turno": "Matutino e Vespertino",
    "campus": "João Pessoa",
    "area_conhecimento": "Ciências Sociais Aplicadas",
    "area_conhecimento_vestibular": "Área IV - CIÊNCIAS HUMANAS E SOCIAIS",
    "modalidade": "Presencial",
    "unidade_responsavel": "CENTRO DE TECNOLOGIA E DESENVOLVIMENTO REGIONAL (CTDR)",
    "unidade_coordenacao": "CTDR - COORDENAÇÃO DE GASTRONOMIA"
  },
  {
    "codigo_inep": "13406",
    "nome_curso": "GEOGRAFIA",
    "grau": "BACHARELADO",
    "turno": "Noturno",
    "campus": "João Pessoa",
    "area_conhecimento": "Ciências Exatas e da Terra",
    "area_conhecimento_vestibular": "Área IV - CIÊNCIAS HUMANAS E SOCIAIS",
    "modalidade": "Presencial",
    "unidade_responsavel": "CENTRO DE CIÊNCIAS EXATAS E DA NATUREZA (CCEN)",
    "unidade_coordenacao": "CCEN - COORDENAÇÃO DE GEOGRAFIA"
  },
  {
    "codigo_inep": "13406",
    "nome_curso": "GEOGRAFIA",
    "grau": "LICENCIATURA",
    "turno": "Noturno",
    "campus": "João Pessoa",
    "area_conhecimento": "Ciências Exatas e da Terra",
    "area_conhecimento_vestibular": "Área IV - CIÊNCIAS HUMANAS E SOCIAIS",
    "modalidade": "Presencial",
    "unidade_responsavel": "CENTRO DE CIÊNCIAS EXATAS E DA NATUREZA (CCEN)",
    "unidade_coordenacao": "CCEN - COORDENAÇÃO DE GEOGRAFIA"
  },
  {
    "codigo_inep": "313406",
    "nome_curso": "GEOGRAFIA",
    "grau": "BACHARELADO",
    "turno": "Matutino e Vespertino",
    "campus": "João Pessoa",
    "area_conhecimento": "Ciências Exatas e da Terra",
    "area_conhecimento_vestibular": "Área IV - CIÊNCIAS HUMANAS E SOCIAIS",
    "modalidade": "Presencial",
    "unidade_responsavel": "CENTRO DE CIÊNCIAS EXATAS E DA NATUREZA (CCEN)",
    "unidade_coordenacao": "CCEN - COORDENAÇÃO DE GEOGRAFIA"
  },
  {
    "codigo_inep": "313406",
    "nome_curso": "GEOGRAFIA",
    "grau": "BACHARELADO",
    "turno": "Noturno",
    "campus": "João Pessoa",
    "area_conhecimento": "Ciências Exatas e da Terra",
    "area_conhecimento_vestibular": "Área IV - CIÊNCIAS HUMANAS E SOCIAIS",
    "modalidade": "Presencial",
    "unidade_responsavel": "CENTRO DE CIÊNCIAS EXATAS E DA NATUREZA (CCEN)",
    "unidade_coordenacao": "CCEN - COORDENAÇÃO DE GEOGRAFIA"
  },
  {
    "codigo_inep": "1363988",
    "nome_curso": "GESTÃO PÚBLICA",
    "grau": "BACHARELADO",
    "turno": "Vespertino",
    "campus": "João Pessoa",
    "area_conhecimento": "Ciências Sociais Aplicadas",
    "area_conhecimento_vestibular": "",
    "modalidade": "Presencial",
    "unidade_responsavel": "CENTRO DE CIÊNCIAS SOCIAIS E APLICADAS (CCSA)",
    "unidade_coordenacao": "CCSA - COORDENAÇÃO DE GESTÃO PÚBLICA"
  },
  {
    "codigo_inep": "13415",
    "nome_curso": "HISTÓRIA",
    "grau": "LICENCIATURA",
    "turno": "Matutino e Vespertino",
    "campus": "João Pessoa",
    "area_conhecimento": "Ciências Humanas",
    "area_conhecimento_vestibular": "Área IV - CIÊNCIAS HUMANAS E SOCIAIS",
    "modalidade": "Presencial",
    "unidade_responsavel": "CENTRO DE CIÊNCIAS HUMANAS, LETRAS E ARTES (CCHLA)",
    "unidade_coordenacao": "CCHLA - COORDENAÇÃO DE HISTÓRIA"
  },
  {
    "codigo_inep": "13415",
    "nome_curso": "HISTÓRIA",
    "grau": "LICENCIATURA",
    "turno": "Noturno",
    "campus": "João Pessoa",
    "area_conhecimento": "Ciências Humanas",
    "area_conhecimento_vestibular": "Área IV - CIÊNCIAS HUMANAS E SOCIAIS",
    "modalidade": "Presencial",
    "unidade_responsavel": "CENTRO DE CIÊNCIAS HUMANAS, LETRAS E ARTES (CCHLA)",
    "unidade_coordenacao": "CCHLA - COORDENAÇÃO DE HISTÓRIA"
  },
  {
    "codigo_inep": "80600",
    "nome_curso": "HISTORIA ( MSC)",
    "grau": "LICENCIATURA",
    "turno": "Matutino e Vespertino",
    "campus": "João Pessoa",
    "area_conhecimento": "Ciências Humanas",
    "area_conhecimento_vestibular": "Área IV - CIÊNCIAS HUMANAS E SOCIAIS",
    "modalidade": "Presencial",
    "unidade_responsavel": "CENTRO DE CIÊNCIAS HUMANAS, LETRAS E ARTES (CCHLA)",
    "unidade_coordenacao": "CCHLA - COORDENAÇÃO DE HISTÓRIA"
  },
  {
    "codigo_inep": "100220",
    "nome_curso": "HOTELARIA",
    "grau": "BACHARELADO",
    "turno": "Matutino e Vespertino",
    "campus": "João Pessoa",
    "area_conhecimento": "Ciências Sociais Aplicadas",
    "area_conhecimento_vestibular": "Área IV - CIÊNCIAS HUMANAS E SOCIAIS",
    "modalidade": "Presencial",
    "unidade_responsavel": "CENTRO DE COMUNICAÇÃO, TURISMO E ARTES (CCTA)",
    "unidade_coordenacao": "CCAE - COORDENAÇÃO DE HOTELARIA E GASTRONOMIA"
  },
  {
    "codigo_inep": "1268219",
    "nome_curso": "JORNALISMO",
    "grau": "BACHARELADO",
    "turno": "Matutino e Vespertino",
    "campus": "João Pessoa",
    "area_conhecimento": "Ciências Sociais Aplicadas",
    "area_conhecimento_vestibular": "Área IV - CIÊNCIAS HUMANAS E SOCIAIS",
    "modalidade": "Presencial",
    "unidade_responsavel": "CENTRO DE COMUNICAÇÃO, TURISMO E ARTES (CCTA)",
    "unidade_coordenacao": "CCTA - COORDENAÇÃO DE JORNALISMO"
  },
  {
    "codigo_inep": "109954",
    "nome_curso": "LETRAS / EAD",
    "grau": "LICENCIATURA",
    "turno": "Matutino e Vespertino",
    "campus": "UFPB VIRTUAL",
    "area_conhecimento": "Ciências Humanas",
    "area_conhecimento_vestibular": "Área IV - CIÊNCIAS HUMANAS E SOCIAIS",
    "modalidade": "A Distância",
    "unidade_responsavel": "CENTRO DE CIÊNCIAS HUMANAS, LETRAS E ARTES (CCHLA)",
    "unidade_coordenacao": "CCHLA - COORDENAÇÃO DE LETRAS (EAD)"
  },
  {
    "codigo_inep": "107553",
    "nome_curso": "LETRAS - ESPANHOL",
    "grau": "LICENCIATURA",
    "turno": "Matutino e Vespertino",
    "campus": "João Pessoa",
    "area_conhecimento": "Ciências Humanas",
    "area_conhecimento_vestibular": "Área IV - CIÊNCIAS HUMANAS E SOCIAIS",
    "modalidade": "Presencial",
    "unidade_responsavel": "CENTRO DE CIÊNCIAS HUMANAS, LETRAS E ARTES (CCHLA)",
    "unidade_coordenacao": "CCHLA - COORDENAÇÃO DE LETRAS"
  },
  {
    "codigo_inep": "1261913",
    "nome_curso": "LETRAS - ESPANHOL",
    "grau": "LICENCIATURA",
    "turno": "Matutino e Vespertino",
    "campus": "UFPB VIRTUAL",
    "area_conhecimento": "Ciências Humanas",
    "area_conhecimento_vestibular": "Área IV - CIÊNCIAS HUMANAS E SOCIAIS",
    "modalidade": "A Distância",
    "unidade_responsavel": "CENTRO DE CIÊNCIAS APLICADAS E EDUCAÇÃO (CCAE)",
    "unidade_coordenacao": "CCAE - COORDENAÇÃO DE LETRAS"
  },
  {
    "codigo_inep": "107552",
    "nome_curso": "LETRAS - FRANCÊS",
    "grau": "LICENCIATURA",
    "turno": "Matutino e Vespertino",
    "campus": "João Pessoa",
    "area_conhecimento": "Ciências Humanas",
    "area_conhecimento_vestibular": "Área IV - CIÊNCIAS HUMANAS E SOCIAIS",
    "modalidade": "Presencial",
    "unidade_responsavel": "CENTRO DE CIÊNCIAS HUMANAS, LETRAS E ARTES (CCHLA)",
    "unidade_coordenacao": "CCHLA - COORDENAÇÃO DE LETRAS"
  },
  {
    "codigo_inep": "107552",
    "nome_curso": "LETRAS - FRANCÊS",
    "grau": "LICENCIATURA",
    "turno": "Noturno",
    "campus": "João Pessoa",
    "area_conhecimento": "Ciências Humanas",
    "area_conhecimento_vestibular": "Área IV - CIÊNCIAS HUMANAS E SOCIAIS",
    "modalidade": "Presencial",
    "unidade_responsavel": "CENTRO DE CIÊNCIAS HUMANAS, LETRAS E ARTES (CCHLA)",
    "unidade_coordenacao": "CCHLA - COORDENAÇÃO DE LETRAS"
  },
  {
    "codigo_inep": "107549",
    "nome_curso": "LETRAS - INGLÊS",
    "grau": "LICENCIATURA",
    "turno": "Matutino e Vespertino",
    "campus": "João Pessoa",
    "area_conhecimento": "Ciências Humanas",
    "area_conhecimento_vestibular": "Área IV - CIÊNCIAS HUMANAS E SOCIAIS",
    "modalidade": "Presencial",
    "unidade_responsavel": "CENTRO DE CIÊNCIAS HUMANAS, LETRAS E ARTES (CCHLA)",
    "unidade_coordenacao": "CCHLA - COORDENAÇÃO DE LETRAS"
  },
  {
    "codigo_inep": "107549",
    "nome_curso": "LETRAS - INGLÊS",
    "grau": "LICENCIATURA",
    "turno": "Noturno",
    "campus": "João Pessoa",
    "area_conhecimento": "Ciências Humanas",
    "area_conhecimento_vestibular": "Área IV - CIÊNCIAS HUMANAS E SOCIAIS",
    "modalidade": "Presencial",
    "unidade_responsavel": "CENTRO DE CIÊNCIAS HUMANAS, LETRAS E ARTES (CCHLA)",
    "unidade_coordenacao": "CCHLA - COORDENAÇÃO DE LETRAS"
  },
  {
    "codigo_inep": "1261910",
    "nome_curso": "LETRAS - INGLÊS",
    "grau": "LICENCIATURA",
    "turno": "Matutino e Vespertino",
    "campus": "UFPB VIRTUAL",
    "area_conhecimento": "Ciências Humanas",
    "area_conhecimento_vestibular": "Área IV - CIÊNCIAS HUMANAS E SOCIAIS",
    "modalidade": "A Distância",
    "unidade_responsavel": "CENTRO DE CIÊNCIAS APLICADAS E EDUCAÇÃO (CCAE)",
    "unidade_coordenacao": "CCAE - COORDENAÇÃO DE LETRAS EM LÍNGUA INGLESA (LICENCIATURA - EAD)"
  },
  {
    "codigo_inep": "116830",
    "nome_curso": "LETRAS - LETRAS CLÁSSICAS (GREGO E LATIM)",
    "grau": "LICENCIATURA",
    "turno": "Noturno",
    "campus": "João Pessoa",
    "area_conhecimento": "Ciências Humanas",
    "area_conhecimento_vestibular": "Área IV - CIÊNCIAS HUMANAS E SOCIAIS",
    "modalidade": "Presencial",
    "unidade_responsavel": "CENTRO DE CIÊNCIAS HUMANAS, LETRAS E ARTES (CCHLA)",
    "unidade_coordenacao": "CCHLA - COORDENAÇÃO DE LETRAS"
  },
  {
    "codigo_inep": "1126690",
    "nome_curso": "LETRAS - LIBRAS",
    "grau": "LICENCIATURA",
    "turno": "Matutino e Vespertino",
    "campus": "UFPB VIRTUAL",
    "area_conhecimento": "Ciências Humanas",
    "area_conhecimento_vestibular": "Área IV - CIÊNCIAS HUMANAS E SOCIAIS",
    "modalidade": "A Distância",
    "unidade_responsavel": "CENTRO DE CIÊNCIAS HUMANAS, LETRAS E ARTES (CCHLA)",
    "unidade_coordenacao": "CCHLA - COORDENAÇÃO DE LETRAS LIBRAS (EAD)"
  },
  {
    "codigo_inep": "5000898",
    "nome_curso": "LETRAS -  LÍNGUA PORTUGUESA",
    "grau": "LICENCIATURA",
    "turno": "Vespertino",
    "campus": "Litoral Norte (Mamanguape e Rio Tinto)",
    "area_conhecimento": "Ciências Humanas",
    "area_conhecimento_vestibular": "Área IV - CIÊNCIAS HUMANAS E SOCIAIS",
    "modalidade": "Presencial",
    "unidade_responsavel": "CENTRO DE CIÊNCIAS APLICADAS E EDUCAÇÃO (CCAE)",
    "unidade_coordenacao": "CCAE - COORDENAÇÃO DE LETRAS"
  },
  {
    "codigo_inep": "107548",
    "nome_curso": "LETRAS - LÍNGUA PORTUGUESA",
    "grau": "LICENCIATURA",
    "turno": "Matutino e Vespertino",
    "campus": "João Pessoa",
    "area_conhecimento": "Ciências Humanas",
    "area_conhecimento_vestibular": "Área IV - CIÊNCIAS HUMANAS E SOCIAIS",
    "modalidade": "Presencial",
    "unidade_responsavel": "CENTRO DE CIÊNCIAS HUMANAS, LETRAS E ARTES (CCHLA)",
    "unidade_coordenacao": "CCHLA - COORDENAÇÃO DE LETRAS"
  },
  {
    "codigo_inep": "107548",
    "nome_curso": "LETRAS - LÍNGUA PORTUGUESA",
    "grau": "LICENCIATURA",
    "turno": "Noturno",
    "campus": "João Pessoa",
    "area_conhecimento": "Ciências Humanas",
    "area_conhecimento_vestibular": "Área IV - CIÊNCIAS HUMANAS E SOCIAIS",
    "modalidade": "Presencial",
    "unidade_responsavel": "CENTRO DE CIÊNCIAS HUMANAS, LETRAS E ARTES (CCHLA)",
    "unidade_coordenacao": "CCHLA - COORDENAÇÃO DE LETRAS"
  },
  {
    "codigo_inep": "107549",
    "nome_curso": "LETRAS - LÍNGUA PORTUGUESA",
    "grau": "LICENCIATURA",
    "turno": "Matutino e Vespertino",
    "campus": "João Pessoa",
    "area_conhecimento": "Ciências Humanas",
    "area_conhecimento_vestibular": "Área IV - CIÊNCIAS HUMANAS E SOCIAIS",
    "modalidade": "Presencial",
    "unidade_responsavel": "CENTRO DE CIÊNCIAS HUMANAS, LETRAS E ARTES (CCHLA)",
    "unidade_coordenacao": "CCHLA - COORDENAÇÃO DE LETRAS"
  },
  {
    "codigo_inep": "107549",
    "nome_curso": "LETRAS - LÍNGUA PORTUGUESA",
    "grau": "LICENCIATURA",
    "turno": "Noturno",
    "campus": "João Pessoa",
    "area_conhecimento": "Ciências Humanas",
    "area_conhecimento_vestibular": "Área IV - CIÊNCIAS HUMANAS E SOCIAIS",
    "modalidade": "Presencial",
    "unidade_responsavel": "CENTRO DE CIÊNCIAS HUMANAS, LETRAS E ARTES (CCHLA)",
    "unidade_coordenacao": "CCHLA - COORDENAÇÃO DE LETRAS"
  },
  {
    "codigo_inep": "44113",
    "nome_curso": "LETRAS - LÍNGUA PORTUGUESA",
    "grau": "LICENCIATURA",
    "turno": "Noturno",
    "campus": "João Pessoa",
    "area_conhecimento": "Ciências Humanas",
    "area_conhecimento_vestibular": "Área IV - CIÊNCIAS HUMANAS E SOCIAIS",
    "modalidade": "Presencial",
    "unidade_responsavel": "CENTRO DE CIÊNCIAS HUMANAS, LETRAS E ARTES (CCHLA)",
    "unidade_coordenacao": "CCHLA - COORDENAÇÃO DE LETRAS"
  },
  {
    "codigo_inep": "44114",
    "nome_curso": "LETRAS - LÍNGUA PORTUGUESA",
    "grau": "LICENCIATURA",
    "turno": "Noturno",
    "campus": "João Pessoa",
    "area_conhecimento": "Ciências Humanas",
    "area_conhecimento_vestibular": "Área IV - CIÊNCIAS HUMANAS E SOCIAIS",
    "modalidade": "Presencial",
    "unidade_responsavel": "CENTRO DE CIÊNCIAS HUMANAS, LETRAS E ARTES (CCHLA)",
    "unidade_coordenacao": "CCHLA - COORDENAÇÃO DE LETRAS"
  },
  {
    "codigo_inep": "122928",
    "nome_curso": "LÍNGUAS ESTRANGEIRAS APLICADAS ÀS NEGOCIAÇÕES INTERNACIONAIS",
    "grau": "BACHARELADO",
    "turno": "Matutino e Vespertino",
    "campus": "João Pessoa",
    "area_conhecimento": "Ciências Humanas",
    "area_conhecimento_vestibular": "Área IV - CIÊNCIAS HUMANAS E SOCIAIS",
    "modalidade": "Presencial",
    "unidade_responsavel": "CENTRO DE CIÊNCIAS HUMANAS, LETRAS E ARTES (CCHLA)",
    "unidade_coordenacao": "CCHLA - COORDENAÇÃO DE LÍNGUAS ESTRANGEIRAS APLICADAS ÀS NEGOCIAÇÕES INTERNACIONAIS"
  },
  {
    "codigo_inep": "118074",
    "nome_curso": "MATEMÁTICA",
    "grau": "BACHARELADO",
    "turno": "Noturno",
    "campus": "João Pessoa",
    "area_conhecimento": "Ciências Exatas e da Terra",
    "area_conhecimento_vestibular": "Área III - CIÊNCIAS EXATAS E TECNOLÓGICAS",
    "modalidade": "Presencial",
    "unidade_responsavel": "CENTRO DE CIÊNCIAS EXATAS E DA NATUREZA (CCEN)",
    "unidade_coordenacao": "CCEN - COORDENAÇÃO DE MATEMÁTICA"
  },
  {
    "codigo_inep": "13402",
    "nome_curso": "MATEMÁTICA",
    "grau": "LICENCIATURA",
    "turno": "Matutino e Vespertino",
    "campus": "João Pessoa",
    "area_conhecimento": "Ciências Exatas e da Terra",
    "area_conhecimento_vestibular": "Área III - CIÊNCIAS EXATAS E TECNOLÓGICAS",
    "modalidade": "Presencial",
    "unidade_responsavel": "CENTRO DE CIÊNCIAS EXATAS E DA NATUREZA (CCEN)",
    "unidade_coordenacao": "CCEN - COORDENAÇÃO DE MATEMÁTICA"
  },
  {
    "codigo_inep": "13402",
    "nome_curso": "MATEMÁTICA",
    "grau": "LICENCIATURA",
    "turno": "Noturno",
    "campus": "João Pessoa",
    "area_conhecimento": "Ciências Exatas e da Terra",
    "area_conhecimento_vestibular": "Área III - CIÊNCIAS EXATAS E TECNOLÓGICAS",
    "modalidade": "Presencial",
    "unidade_responsavel": "CENTRO DE CIÊNCIAS EXATAS E DA NATUREZA (CCEN)",
    "unidade_coordenacao": "CCEN - COORDENAÇÃO DE MATEMÁTICA"
  },
  {
    "codigo_inep": "313402",
    "nome_curso": "MATEMÁTICA",
    "grau": "BACHARELADO",
    "turno": "Matutino e Vespertino",
    "campus": "João Pessoa",
    "area_conhecimento": "Ciências Exatas e da Terra",
    "area_conhecimento_vestibular": "Área III - CIÊNCIAS EXATAS E TECNOLÓGICAS",
    "modalidade": "Presencial",
    "unidade_responsavel": "CENTRO DE CIÊNCIAS EXATAS E DA NATUREZA (CCEN)",
    "unidade_coordenacao": "CCEN - COORDENAÇÃO DE MATEMÁTICA"
  },
  {
    "codigo_inep": "1162837",
    "nome_curso": "MATEMÁTICA COMPUTACIONAL",
    "grau": "BACHARELADO",
    "turno": "Matutino e Vespertino",
    "campus": "João Pessoa",
    "area_conhecimento": "Engenharias",
    "area_conhecimento_vestibular": "Área III - CIÊNCIAS EXATAS E TECNOLÓGICAS",
    "modalidade": "Presencial",
    "unidade_responsavel": "CENTRO DE INFORMÁTICA (CI)",
    "unidade_coordenacao": "CI - COORDENAÇÃO DE MATEMÁTICA COMPUTACIONAL"
  },
  {
    "codigo_inep": "109948",
    "nome_curso": "MATEMÁTICA - EAD",
    "grau": "LICENCIATURA",
    "turno": "Matutino e Vespertino",
    "campus": "UFPB VIRTUAL",
    "area_conhecimento": "Ciências Exatas e da Terra",
    "area_conhecimento_vestibular": "Área III - CIÊNCIAS EXATAS E TECNOLÓGICAS",
    "modalidade": "A Distância",
    "unidade_responsavel": "CENTRO DE CIÊNCIAS EXATAS E DA NATUREZA (CCEN)",
    "unidade_coordenacao": "CCEN - COORDENAÇÃO DE MATEMÁTICA"
  },
  {
    "codigo_inep": "99045",
    "nome_curso": "MATEMÁTICA (LICENCIATURA)",
    "grau": "LICENCIATURA",
    "turno": "Noturno",
    "campus": "Litoral Norte (Mamanguape e Rio Tinto)",
    "area_conhecimento": "Ciências Exatas e da Terra",
    "area_conhecimento_vestibular": "Área III - CIÊNCIAS EXATAS E TECNOLÓGICAS",
    "modalidade": "Presencial",
    "unidade_responsavel": "CENTRO DE CIÊNCIAS APLICADAS E EDUCAÇÃO (CCAE)",
    "unidade_coordenacao": "CCAE - COORDENAÇÃO DE MATEMÁTICA (LICENCIATURA)"
  },
  {
    "codigo_inep": "13424",
    "nome_curso": "MEDICINA",
    "grau": "BACHARELADO",
    "turno": "Matutino e Vespertino",
    "campus": "João Pessoa",
    "area_conhecimento": "Ciências da Saúde",
    "area_conhecimento_vestibular": "Área II -CIÊNCIAS BIOLÓGICAS E DA SAÚDE",
    "modalidade": "Presencial",
    "unidade_responsavel": "CENTRO DE CIENCIAS MEDICAS (CCM)",
    "unidade_coordenacao": "CCM - COORDENAÇÃO DE MEDICINA"
  },
  {
    "codigo_inep": "113709",
    "nome_curso": "MEDICINA VETERINÁRIA",
    "grau": "BACHARELADO",
    "turno": "Matutino e Vespertino",
    "campus": "Areia",
    "area_conhecimento": "Ciências Agrárias",
    "area_conhecimento_vestibular": "Área I - CIÊNCIAS AGRÁRIAS",
    "modalidade": "Presencial",
    "unidade_responsavel": "CENTRO DE CIÊNCIAS AGRÁRIAS (CCA)",
    "unidade_coordenacao": "CCA - COORDENAÇÃO DE MEDICINA VETERINÁRIA"
  },
  {
    "codigo_inep": "97039",
    "nome_curso": "MÚSICA",
    "grau": "LICENCIATURA",
    "turno": "Matutino e Vespertino",
    "campus": "João Pessoa",
    "area_conhecimento": "Ciências Humanas",
    "area_conhecimento_vestibular": "Área V - ARTÍSTICA",
    "modalidade": "Presencial",
    "unidade_responsavel": "CENTRO DE COMUNICAÇÃO, TURISMO E ARTES (CCTA)",
    "unidade_coordenacao": "CCTA - COORDENAÇÃO DE MÚSICA (LICENCIATURA)"
  },
  {
    "codigo_inep": "97040",
    "nome_curso": "MÚSICA",
    "grau": "LICENCIATURA",
    "turno": "Matutino e Vespertino",
    "campus": "João Pessoa",
    "area_conhecimento": "Ciências Humanas",
    "area_conhecimento_vestibular": "Área V - ARTÍSTICA",
    "modalidade": "Presencial",
    "unidade_responsavel": "CENTRO DE COMUNICAÇÃO, TURISMO E ARTES (CCTA)",
    "unidade_coordenacao": "CCTA - COORDENAÇÃO DE MÚSICA (LICENCIATURA)"
  },
  {
    "codigo_inep": "97041",
    "nome_curso": "MÚSICA",
    "grau": "LICENCIATURA",
    "turno": "Matutino e Vespertino",
    "campus": "João Pessoa",
    "area_conhecimento": "Ciências Humanas",
    "area_conhecimento_vestibular": "Área V - ARTÍSTICA",
    "modalidade": "Presencial",
    "unidade_responsavel": "CENTRO DE COMUNICAÇÃO, TURISMO E ARTES (CCTA)",
    "unidade_coordenacao": "CCTA - COORDENAÇÃO DE MÚSICA (LICENCIATURA)"
  },
  {
    "codigo_inep": "26564",
    "nome_curso": "MÚSICA - BACHARELADO",
    "grau": "BACHARELADO",
    "turno": "Matutino e Vespertino",
    "campus": "João Pessoa",
    "area_conhecimento": "Ciências Humanas",
    "area_conhecimento_vestibular": "Área V - ARTÍSTICA",
    "modalidade": "Presencial",
    "unidade_responsavel": "CENTRO DE COMUNICAÇÃO, TURISMO E ARTES (CCTA)",
    "unidade_coordenacao": "CCTA - COORDENAÇÃO DE MÚSICA (BACHARELADO)"
  },
  {
    "codigo_inep": "123240",
    "nome_curso": "MUSICA POPULAR",
    "grau": "OUTRO TIPO DE GRAU ACADÊMICO",
    "turno": "Noturno",
    "campus": "João Pessoa",
    "area_conhecimento": "Ciências Humanas",
    "area_conhecimento_vestibular": "Área V - ARTÍSTICA",
    "modalidade": "Presencial",
    "unidade_responsavel": "CENTRO DE COMUNICAÇÃO, TURISMO E ARTES (CCTA)",
    "unidade_coordenacao": "CCTA - COORDENAÇÃO DE REGÊNCIA DE BANDAS E FANFARRAS (SEQUENCIAL)"
  },
  {
    "codigo_inep": "13425",
    "nome_curso": "NUTRIÇÃO",
    "grau": "BACHARELADO",
    "turno": "Matutino e Vespertino",
    "campus": "João Pessoa",
    "area_conhecimento": "Ciências da Saúde",
    "area_conhecimento_vestibular": "Área II -CIÊNCIAS BIOLÓGICAS E DA SAÚDE",
    "modalidade": "Presencial",
    "unidade_responsavel": "CENTRO DE CIÊNCIAS DA SAÚDE (CCS)",
    "unidade_coordenacao": "CCS - COORDENAÇÃO DE NUTRIÇÃO"
  },
  {
    "codigo_inep": "13426",
    "nome_curso": "ODONTOLOGIA",
    "grau": "BACHARELADO",
    "turno": "Matutino e Vespertino",
    "campus": "João Pessoa",
    "area_conhecimento": "Ciências da Saúde",
    "area_conhecimento_vestibular": "Área II -CIÊNCIAS BIOLÓGICAS E DA SAÚDE",
    "modalidade": "Presencial",
    "unidade_responsavel": "CENTRO DE CIÊNCIAS DA SAÚDE (CCS)",
    "unidade_coordenacao": "CCS - COORDENAÇÃO DE ODONTOLOGIA"
  },
  {
    "codigo_inep": "107356",
    "nome_curso": "PEDAGOGIA",
    "grau": "LICENCIATURA",
    "turno": "Noturno",
    "campus": "Litoral Norte (Mamanguape e Rio Tinto)",
    "area_conhecimento": "Ciências Humanas",
    "area_conhecimento_vestibular": "Área IV - CIÊNCIAS HUMANAS E SOCIAIS",
    "modalidade": "Presencial",
    "unidade_responsavel": "CENTRO DE CIÊNCIAS APLICADAS E EDUCAÇÃO (CCAE)",
    "unidade_coordenacao": "CCAE - COORDENAÇÃO DE PEDAGOGIA"
  },
  {
    "codigo_inep": "109626",
    "nome_curso": "PEDAGOGIA",
    "grau": "LICENCIATURA",
    "turno": "Matutino e Vespertino",
    "campus": "Bananeiras",
    "area_conhecimento": "Ciências Humanas",
    "area_conhecimento_vestibular": "Área IV - CIÊNCIAS HUMANAS E SOCIAIS",
    "modalidade": "Presencial",
    "unidade_responsavel": "CENTRO DE CIÊNCIAS HUMANAS SOCIAIS E AGRÁRIAS (CCHSA)",
    "unidade_coordenacao": "CCHSA - COORDENAÇÃO DE PEDAGOGIA (LICENCIATURA)"
  },
  {
    "codigo_inep": "109626",
    "nome_curso": "PEDAGOGIA",
    "grau": "LICENCIATURA",
    "turno": "Noturno",
    "campus": "Bananeiras",
    "area_conhecimento": "Ciências Humanas",
    "area_conhecimento_vestibular": "Área IV - CIÊNCIAS HUMANAS E SOCIAIS",
    "modalidade": "Presencial",
    "unidade_responsavel": "CENTRO DE CIÊNCIAS HUMANAS SOCIAIS E AGRÁRIAS (CCHSA)",
    "unidade_coordenacao": "CCHSA - COORDENAÇÃO DE PEDAGOGIA (LICENCIATURA)"
  },
  {
    "codigo_inep": "13418",
    "nome_curso": "PEDAGOGIA",
    "grau": "LICENCIATURA",
    "turno": "Matutino",
    "campus": "João Pessoa",
    "area_conhecimento": "Ciências Humanas",
    "area_conhecimento_vestibular": "Área IV - CIÊNCIAS HUMANAS E SOCIAIS",
    "modalidade": "Presencial",
    "unidade_responsavel": "CENTRO DE EDUCAÇÃO (CE)",
    "unidade_coordenacao": "CE - COORDENAÇÃO DE PEDAGOGIA (LICENCIATURA)"
  },
  {
    "codigo_inep": "13418",
    "nome_curso": "PEDAGOGIA",
    "grau": "LICENCIATURA",
    "turno": "Matutino e Vespertino",
    "campus": "João Pessoa",
    "area_conhecimento": "Ciências Humanas",
    "area_conhecimento_vestibular": "Área IV - CIÊNCIAS HUMANAS E SOCIAIS",
    "modalidade": "Presencial",
    "unidade_responsavel": "CENTRO DE EDUCAÇÃO (CE)",
    "unidade_coordenacao": "CE - COORDENAÇÃO DE PEDAGOGIA (LICENCIATURA)"
  },
  {
    "codigo_inep": "13418",
    "nome_curso": "PEDAGOGIA",
    "grau": "LICENCIATURA",
    "turno": "Noturno",
    "campus": "João Pessoa",
    "area_conhecimento": "Ciências Humanas",
    "area_conhecimento_vestibular": "Área IV - CIÊNCIAS HUMANAS E SOCIAIS",
    "modalidade": "Presencial",
    "unidade_responsavel": "CENTRO DE EDUCAÇÃO (CE)",
    "unidade_coordenacao": "CE - COORDENAÇÃO DE PEDAGOGIA (LICENCIATURA)"
  },
  {
    "codigo_inep": "13418",
    "nome_curso": "PEDAGOGIA",
    "grau": "LICENCIATURA",
    "turno": "Vespertino",
    "campus": "João Pessoa",
    "area_conhecimento": "Ciências Humanas",
    "area_conhecimento_vestibular": "Área IV - CIÊNCIAS HUMANAS E SOCIAIS",
    "modalidade": "Presencial",
    "unidade_responsavel": "CENTRO DE EDUCAÇÃO (CE)",
    "unidade_coordenacao": "CE - COORDENAÇÃO DE PEDAGOGIA (LICENCIATURA)"
  },
  {
    "codigo_inep": "13418",
    "nome_curso": "PEDAGOGIA",
    "grau": "LICENCIATURA PLENA",
    "turno": "Matutino e Vespertino",
    "campus": "João Pessoa",
    "area_conhecimento": "Ciências Humanas",
    "area_conhecimento_vestibular": "Área IV - CIÊNCIAS HUMANAS E SOCIAIS",
    "modalidade": "Presencial",
    "unidade_responsavel": "CENTRO DE EDUCAÇÃO (CE)",
    "unidade_coordenacao": "CE - COORDENAÇÃO DE PEDAGOGIA (LICENCIATURA)"
  },
  {
    "codigo_inep": "109950",
    "nome_curso": "PEDAGOGIA - EAD",
    "grau": "LICENCIATURA",
    "turno": "Matutino e Vespertino",
    "campus": "UFPB VIRTUAL",
    "area_conhecimento": "Ciências Humanas",
    "area_conhecimento_vestibular": "Área IV - CIÊNCIAS HUMANAS E SOCIAIS",
    "modalidade": "A Distância",
    "unidade_responsavel": "CENTRO DE EDUCAÇÃO (CE)",
    "unidade_coordenacao": "CE - COORDENAÇÃO DE PEDAGOGIA (EAD)"
  },
  {
    "codigo_inep": "122924",
    "nome_curso": "PEDAGOGIA - EDUCAÇÃO DO CAMPO",
    "grau": "LICENCIATURA",
    "turno": "Noturno",
    "campus": "João Pessoa",
    "area_conhecimento": "Ciências Humanas",
    "area_conhecimento_vestibular": "Área IV - CIÊNCIAS HUMANAS E SOCIAIS",
    "modalidade": "Presencial",
    "unidade_responsavel": "CENTRO DE EDUCAÇÃO (CE)",
    "unidade_coordenacao": "CE - COORDENAÇÃO DE PEDAGOGIA (LICENCIATURA)"
  },
  {
    "codigo_inep": "113707",
    "nome_curso": "PEDAGOGIA (MSC)",
    "grau": "LICENCIATURA",
    "turno": "Matutino e Vespertino",
    "campus": "João Pessoa",
    "area_conhecimento": "Ciências Humanas",
    "area_conhecimento_vestibular": "Área IV - CIÊNCIAS HUMANAS E SOCIAIS",
    "modalidade": "Presencial",
    "unidade_responsavel": "CENTRO DE EDUCAÇÃO (CE)",
    "unidade_coordenacao": "CE - COORDENAÇÃO DE PEDAGOGIA (LICENCIATURA)"
  },
  {
    "codigo_inep": "13413",
    "nome_curso": "PSICOLOGIA",
    "grau": "BACHARELADO",
    "turno": "Matutino e Vespertino",
    "campus": "João Pessoa",
    "area_conhecimento": "Ciências Humanas",
    "area_conhecimento_vestibular": "Área IV - CIÊNCIAS HUMANAS E SOCIAIS",
    "modalidade": "Presencial",
    "unidade_responsavel": "CENTRO DE CIÊNCIAS HUMANAS, LETRAS E ARTES (CCHLA)",
    "unidade_coordenacao": "CCHLA - COORDENAÇÃO DE PSICOLOGIA"
  },
  {
    "codigo_inep": "26565",
    "nome_curso": "PSICOLOGIA",
    "grau": "LICENCIATURA",
    "turno": "Matutino e Vespertino",
    "campus": "João Pessoa",
    "area_conhecimento": "Ciências Humanas",
    "area_conhecimento_vestibular": "Área IV - CIÊNCIAS HUMANAS E SOCIAIS",
    "modalidade": "Presencial",
    "unidade_responsavel": "CENTRO DE CIÊNCIAS HUMANAS, LETRAS E ARTES (CCHLA)",
    "unidade_coordenacao": "CCHLA - COORDENAÇÃO DE PSICOLOGIA"
  },
  {
    "codigo_inep": "122926",
    "nome_curso": "PSICOPEDAGOGIA (BACH)",
    "grau": "BACHARELADO",
    "turno": "Matutino e Vespertino",
    "campus": "João Pessoa",
    "area_conhecimento": "Ciências Humanas",
    "area_conhecimento_vestibular": "Área IV - CIÊNCIAS HUMANAS E SOCIAIS",
    "modalidade": "Presencial",
    "unidade_responsavel": "CENTRO DE EDUCAÇÃO (CE)",
    "unidade_coordenacao": "CE - COORDENAÇÃO DE PSICOPEDAGOGIA"
  },
  {
    "codigo_inep": "122926",
    "nome_curso": "PSICOPEDAGOGIA (BACH)",
    "grau": "BACHARELADO",
    "turno": "Vespertino",
    "campus": "João Pessoa",
    "area_conhecimento": "Ciências Humanas",
    "area_conhecimento_vestibular": "Área IV - CIÊNCIAS HUMANAS E SOCIAIS",
    "modalidade": "Presencial",
    "unidade_responsavel": "CENTRO DE EDUCAÇÃO (CE)",
    "unidade_coordenacao": "CE - COORDENAÇÃO DE PSICOPEDAGOGIA"
  },
  {
    "codigo_inep": "1161324",
    "nome_curso": "QUÍMICA",
    "grau": "LICENCIATURA",
    "turno": "Noturno",
    "campus": "Areia",
    "area_conhecimento": "Ciências Exatas e da Terra",
    "area_conhecimento_vestibular": "Área III - CIÊNCIAS EXATAS E TECNOLÓGICAS",
    "modalidade": "Presencial",
    "unidade_responsavel": "CENTRO DE CIÊNCIAS AGRÁRIAS (CCA)",
    "unidade_coordenacao": "CCA - COORDENAÇÃO DE QUÍMICA"
  },
  {
    "codigo_inep": "118076",
    "nome_curso": "QUÍMICA",
    "grau": "LICENCIATURA CURTA",
    "turno": "Noturno",
    "campus": "João Pessoa",
    "area_conhecimento": "Ciências Exatas e da Terra",
    "area_conhecimento_vestibular": "Área III - CIÊNCIAS EXATAS E TECNOLÓGICAS",
    "modalidade": "Presencial",
    "unidade_responsavel": "CENTRO DE CIÊNCIAS EXATAS E DA NATUREZA (CCEN)",
    "unidade_coordenacao": "CT - COORDENAÇÃO DO CURSO DE QUÍMICA INDUSTRIAL"
  },
  {
    "codigo_inep": "13404",
    "nome_curso": "QUÍMICA",
    "grau": "LICENCIATURA",
    "turno": "Matutino e Vespertino",
    "campus": "João Pessoa",
    "area_conhecimento": "Ciências Exatas e da Terra",
    "area_conhecimento_vestibular": "Área III - CIÊNCIAS EXATAS E TECNOLÓGICAS",
    "modalidade": "Presencial",
    "unidade_responsavel": "CENTRO DE CIÊNCIAS EXATAS E DA NATUREZA (CCEN)",
    "unidade_coordenacao": "CT - COORDENAÇÃO DO CURSO DE QUÍMICA INDUSTRIAL"
  },
  {
    "codigo_inep": "13404",
    "nome_curso": "QUÍMICA",
    "grau": "LICENCIATURA",
    "turno": "Noturno",
    "campus": "João Pessoa",
    "area_conhecimento": "Ciências Exatas e da Terra",
    "area_conhecimento_vestibular": "Área III - CIÊNCIAS EXATAS E TECNOLÓGICAS",
    "modalidade": "Presencial",
    "unidade_responsavel": "CENTRO DE CIÊNCIAS EXATAS E DA NATUREZA (CCEN)",
    "unidade_coordenacao": "CT - COORDENAÇÃO DO CURSO DE QUÍMICA INDUSTRIAL"
  },
  {
    "codigo_inep": "313404",
    "nome_curso": "QUÍMICA",
    "grau": "BACHARELADO",
    "turno": "Matutino e Vespertino",
    "campus": "João Pessoa",
    "area_conhecimento": "Ciências Exatas e da Terra",
    "area_conhecimento_vestibular": "Área III - CIÊNCIAS EXATAS E TECNOLÓGICAS",
    "modalidade": "Presencial",
    "unidade_responsavel": "CENTRO DE CIÊNCIAS EXATAS E DA NATUREZA (CCEN)",
    "unidade_coordenacao": "CT - COORDENAÇÃO DO CURSO DE QUÍMICA INDUSTRIAL"
  },
  {
    "codigo_inep": "5000897",
    "nome_curso": "QUÍMICA",
    "grau": "BACHARELADO",
    "turno": "Noturno",
    "campus": "Areia",
    "area_conhecimento": "Ciências Exatas e da Terra",
    "area_conhecimento_vestibular": "Área III - CIÊNCIAS EXATAS E TECNOLÓGICAS",
    "modalidade": "Presencial",
    "unidade_responsavel": "CENTRO DE CIÊNCIAS AGRÁRIAS (CCA)",
    "unidade_coordenacao": "CCA - COORDENAÇÃO DE QUÍMICA"
  },
  {
    "codigo_inep": "13431",
    "nome_curso": "QUÍMICA INDUSTRIAL",
    "grau": "BACHARELADO",
    "turno": "Matutino e Vespertino",
    "campus": "João Pessoa",
    "area_conhecimento": "Engenharias",
    "area_conhecimento_vestibular": "Área III - CIÊNCIAS EXATAS E TECNOLÓGICAS",
    "modalidade": "Presencial",
    "unidade_responsavel": "CENTRO DE TECNOLOGIA (CT)",
    "unidade_coordenacao": "CT - COORDENAÇÃO DO CURSO DE QUÍMICA INDUSTRIAL"
  },
  {
    "codigo_inep": "1268221",
    "nome_curso": "RADIALISMO",
    "grau": "BACHARELADO",
    "turno": "Matutino e Vespertino",
    "campus": "João Pessoa",
    "area_conhecimento": "Ciências Sociais Aplicadas",
    "area_conhecimento_vestibular": "Área IV - CIÊNCIAS HUMANAS E SOCIAIS",
    "modalidade": "Presencial",
    "unidade_responsavel": "CENTRO DE COMUNICAÇÃO, TURISMO E ARTES (CCTA)",
    "unidade_coordenacao": "CCTA - COORDENAÇÃO DE RADIALISMO"
  },
  {
    "codigo_inep": "123241",
    "nome_curso": "REGÊNCIA DE BANDAS E FANFARRAS",
    "grau": "OUTRO TIPO DE GRAU ACADÊMICO",
    "turno": "Noturno",
    "campus": "João Pessoa",
    "area_conhecimento": "Ciências Humanas",
    "area_conhecimento_vestibular": "Área V - ARTÍSTICA",
    "modalidade": "Presencial",
    "unidade_responsavel": "CENTRO DE COMUNICAÇÃO, TURISMO E ARTES (CCTA)",
    "unidade_coordenacao": "CCTA - COORDENAÇÃO DE REGÊNCIA DE BANDAS E FANFARRAS (SEQUENCIAL)"
  },
  {
    "codigo_inep": "1126958",
    "nome_curso": "RELACÕES INTERNACIONAIS",
    "grau": "BACHARELADO",
    "turno": "Matutino e Vespertino",
    "campus": "João Pessoa",
    "area_conhecimento": "Ciências Sociais Aplicadas",
    "area_conhecimento_vestibular": "Área IV - CIÊNCIAS HUMANAS E SOCIAIS",
    "modalidade": "Presencial",
    "unidade_responsavel": "CENTRO DE CIÊNCIAS SOCIAIS E APLICADAS (CCSA)",
    "unidade_coordenacao": "CCSA - COORDENACÃO DE RELAÇÕES INTERNACIONAIS"
  },
  {
    "codigo_inep": "1126958",
    "nome_curso": "RELACÕES INTERNACIONAIS",
    "grau": "BACHARELADO",
    "turno": "Noturno",
    "campus": "João Pessoa",
    "area_conhecimento": "Ciências Sociais Aplicadas",
    "area_conhecimento_vestibular": "Área IV - CIÊNCIAS HUMANAS E SOCIAIS",
    "modalidade": "Presencial",
    "unidade_responsavel": "CENTRO DE CIÊNCIAS SOCIAIS E APLICADAS (CCSA)",
    "unidade_coordenacao": "CCSA - COORDENACÃO DE RELAÇÕES INTERNACIONAIS"
  },
  {
    "codigo_inep": "1268257",
    "nome_curso": "RELAÇÕES PÚBLICAS",
    "grau": "BACHARELADO",
    "turno": "Noturno",
    "campus": "João Pessoa",
    "area_conhecimento": "Ciências Sociais Aplicadas",
    "area_conhecimento_vestibular": "Área IV - CIÊNCIAS HUMANAS E SOCIAIS",
    "modalidade": "Presencial",
    "unidade_responsavel": "CENTRO DE COMUNICAÇÃO, TURISMO E ARTES (CCTA)",
    "unidade_coordenacao": "CCTA - COORDENAÇÃO DE RELAÇÕES PÚBLICAS"
  },
  {
    "codigo_inep": "98982",
    "nome_curso": "SECRETARIADO EXECUTIVO BILÍNGUE",
    "grau": "BACHARELADO",
    "turno": "Noturno",
    "campus": "Litoral Norte (Mamanguape e Rio Tinto)",
    "area_conhecimento": "Ciências Sociais Aplicadas",
    "area_conhecimento_vestibular": "Área IV - CIÊNCIAS HUMANAS E SOCIAIS",
    "modalidade": "Presencial",
    "unidade_responsavel": "CENTRO DE CIÊNCIAS APLICADAS E EDUCAÇÃO (CCAE)",
    "unidade_coordenacao": "CCAE - COORDENAÇÃO DE SECRETARIADO EXECUTIVO BILÍNGUE"
  },
  {
    "codigo_inep": "13417",
    "nome_curso": "SERVIÇO SOCIAL",
    "grau": "BACHARELADO",
    "turno": "Noturno",
    "campus": "João Pessoa",
    "area_conhecimento": "Ciências Humanas",
    "area_conhecimento_vestibular": "Área IV - CIÊNCIAS HUMANAS E SOCIAIS",
    "modalidade": "Presencial",
    "unidade_responsavel": "CENTRO DE CIÊNCIAS HUMANAS, LETRAS E ARTES (CCHLA)",
    "unidade_coordenacao": "CCHLA - COORDENAÇÃO DE SERVIÇO SOCIAL"
  },
  {
    "codigo_inep": "13417",
    "nome_curso": "SERVIÇO SOCIAL",
    "grau": "BACHARELADO",
    "turno": "Vespertino",
    "campus": "João Pessoa",
    "area_conhecimento": "Ciências Humanas",
    "area_conhecimento_vestibular": "Área IV - CIÊNCIAS HUMANAS E SOCIAIS",
    "modalidade": "Presencial",
    "unidade_responsavel": "CENTRO DE CIÊNCIAS HUMANAS, LETRAS E ARTES (CCHLA)",
    "unidade_coordenacao": "CCHLA - COORDENAÇÃO DE SERVIÇO SOCIAL"
  },
  {
    "codigo_inep": "107360",
    "nome_curso": "SISTEMAS DE INFORMAÇÃO",
    "grau": "BACHARELADO",
    "turno": "Matutino e Vespertino",
    "campus": "Litoral Norte (Mamanguape e Rio Tinto)",
    "area_conhecimento": "Engenharias",
    "area_conhecimento_vestibular": "Área III - CIÊNCIAS EXATAS E TECNOLÓGICAS",
    "modalidade": "Presencial",
    "unidade_responsavel": "CENTRO DE CIÊNCIAS APLICADAS E EDUCAÇÃO (CCAE)",
    "unidade_coordenacao": "CCAE - COORDENAÇÃO DE SISTEMAS DE INFORMAÇÃO (BACHARELADO)"
  },
  {
    "codigo_inep": "407456",
    "nome_curso": "TEATRO (BACHARELADO)",
    "grau": "BACHARELADO",
    "turno": "Matutino e Vespertino",
    "campus": "João Pessoa",
    "area_conhecimento": "Ciências Humanas",
    "area_conhecimento_vestibular": "Área V - ARTÍSTICA",
    "modalidade": "Presencial",
    "unidade_responsavel": "CENTRO DE COMUNICAÇÃO, TURISMO E ARTES (CCTA)",
    "unidade_coordenacao": "CCTA - COORDENAÇÃO DE TEATRO (BACHARELADO)"
  },
  {
    "codigo_inep": "107456",
    "nome_curso": "TEATRO (LICENCIATURA)",
    "grau": "LICENCIATURA",
    "turno": "Matutino e Vespertino",
    "campus": "João Pessoa",
    "area_conhecimento": "Ciências Humanas",
    "area_conhecimento_vestibular": "Área V - ARTÍSTICA",
    "modalidade": "Presencial",
    "unidade_responsavel": "CENTRO DE COMUNICAÇÃO, TURISMO E ARTES (CCTA)",
    "unidade_coordenacao": "CCTA - COORDENAÇÃO DE TEATRO (BACHARELADO)"
  },
  {
    "codigo_inep": "1127907",
    "nome_curso": "TECNOLOGIA DE ALIMENTOS",
    "grau": "TECNOLÓGICO",
    "turno": "Noturno",
    "campus": "João Pessoa",
    "area_conhecimento": "Engenharias",
    "area_conhecimento_vestibular": "Área III - CIÊNCIAS EXATAS E TECNOLÓGICAS",
    "modalidade": "Presencial",
    "unidade_responsavel": "CENTRO DE TECNOLOGIA E DESENVOLVIMENTO REGIONAL (CTDR)",
    "unidade_coordenacao": "CTDR - COORDENAÇÃO DE TECNOLOGIA DE ALIMENTOS"
  },
  {
    "codigo_inep": "1127907",
    "nome_curso": "TECNOLOGIA DE ALIMENTOS",
    "grau": "TECNOLÓGICO",
    "turno": "Vespertino",
    "campus": "João Pessoa",
    "area_conhecimento": "Engenharias",
    "area_conhecimento_vestibular": "Área III - CIÊNCIAS EXATAS E TECNOLÓGICAS",
    "modalidade": "Presencial",
    "unidade_responsavel": "CENTRO DE TECNOLOGIA E DESENVOLVIMENTO REGIONAL (CTDR)",
    "unidade_coordenacao": "CTDR - COORDENAÇÃO DE TECNOLOGIA DE ALIMENTOS"
  },
  {
    "codigo_inep": "1125642",
    "nome_curso": "TECNOLOGIA EM GESTÃO PÚBLICA",
    "grau": "TECNOLÓGICO",
    "turno": "Noturno",
    "campus": "João Pessoa",
    "area_conhecimento": "Ciências Sociais Aplicadas",
    "area_conhecimento_vestibular": "Área IV - CIÊNCIAS HUMANAS E SOCIAIS",
    "modalidade": "Presencial",
    "unidade_responsavel": "CENTRO DE CIÊNCIAS SOCIAIS E APLICADAS (CCSA)",
    "unidade_coordenacao": "CCSA - COORDENAÇÃO DE GESTÃO PÚBLICA"
  },
  {
    "codigo_inep": "1125642",
    "nome_curso": "TECNOLOGIA EM GESTÃO PÚBLICA",
    "grau": "TECNOLÓGICO",
    "turno": "Vespertino",
    "campus": "João Pessoa",
    "area_conhecimento": "Ciências Sociais Aplicadas",
    "area_conhecimento_vestibular": "Área IV - CIÊNCIAS HUMANAS E SOCIAIS",
    "modalidade": "Presencial",
    "unidade_responsavel": "CENTRO DE CIÊNCIAS SOCIAIS E APLICADAS (CCSA)",
    "unidade_coordenacao": "CCSA - COORDENAÇÃO DE GESTÃO PÚBLICA"
  },
  {
    "codigo_inep": "1127165",
    "nome_curso": "TECNOLOGIA EM PRODUÇÃO SUCROALCOOLEIRA",
    "grau": "TECNOLÓGICO",
    "turno": "Noturno",
    "campus": "João Pessoa",
    "area_conhecimento": "Engenharias",
    "area_conhecimento_vestibular": "Área III - CIÊNCIAS EXATAS E TECNOLÓGICAS",
    "modalidade": "Presencial",
    "unidade_responsavel": "CENTRO DE TECNOLOGIA E DESENVOLVIMENTO REGIONAL (CTDR)",
    "unidade_coordenacao": "CTDR - COORDENAÇÃO DE TECNOLOGIA SUCROALCOLEIRA"
  },
  {
    "codigo_inep": "1127165",
    "nome_curso": "TECNOLOGIA EM PRODUÇÃO SUCROALCOOLEIRA",
    "grau": "TECNOLÓGICO",
    "turno": "Vespertino",
    "campus": "João Pessoa",
    "area_conhecimento": "Engenharias",
    "area_conhecimento_vestibular": "Área III - CIÊNCIAS EXATAS E TECNOLÓGICAS",
    "modalidade": "Presencial",
    "unidade_responsavel": "CENTRO DE TECNOLOGIA E DESENVOLVIMENTO REGIONAL (CTDR)",
    "unidade_coordenacao": "CTDR - COORDENAÇÃO DE TECNOLOGIA SUCROALCOLEIRA"
  },
  {
    "codigo_inep": "1123330",
    "nome_curso": "TERAPIA OCUPACIONAL",
    "grau": "BACHARELADO",
    "turno": "Matutino e Vespertino",
    "campus": "João Pessoa",
    "area_conhecimento": "Ciências da Saúde",
    "area_conhecimento_vestibular": "Área II -CIÊNCIAS BIOLÓGICAS E DA SAÚDE",
    "modalidade": "Presencial",
    "unidade_responsavel": "CENTRO DE CIÊNCIAS DA SAÚDE (CCS)",
    "unidade_coordenacao": "CCS - COORDENAÇÃO DE TERAPIA OCUPACIONAL"
  },
  {
    "codigo_inep": "122930",
    "nome_curso": "TRADUÇÃO",
    "grau": "BACHARELADO",
    "turno": "Matutino e Vespertino",
    "campus": "João Pessoa",
    "area_conhecimento": "Ciências Humanas",
    "area_conhecimento_vestibular": "Área IV - CIÊNCIAS HUMANAS E SOCIAIS",
    "modalidade": "Presencial",
    "unidade_responsavel": "CENTRO DE CIÊNCIAS HUMANAS, LETRAS E ARTES (CCHLA)",
    "unidade_coordenacao": "CCHLA - COORDENAÇÃO DE TRADUÇÃO (BACHARELADO)"
  },
  {
    "codigo_inep": "19562",
    "nome_curso": "TURISMO",
    "grau": "BACHARELADO",
    "turno": "Noturno",
    "campus": "João Pessoa",
    "area_conhecimento": "Ciências Sociais Aplicadas",
    "area_conhecimento_vestibular": "Área IV - CIÊNCIAS HUMANAS E SOCIAIS",
    "modalidade": "Presencial",
    "unidade_responsavel": "CENTRO DE COMUNICAÇÃO, TURISMO E ARTES (CCTA)",
    "unidade_coordenacao": "CCTA - COORDENAÇÃO DE TURISMO"
  },
  {
    "codigo_inep": "13403",
    "nome_curso": "ZOOTECNIA",
    "grau": "BACHARELADO",
    "turno": "Matutino e Vespertino",
    "campus": "Areia",
    "area_conhecimento": "Ciências Agrárias",
    "area_conhecimento_vestibular": "Área I - CIÊNCIAS AGRÁRIAS",
    "modalidade": "Presencial",
    "unidade_responsavel": "CENTRO DE CIÊNCIAS AGRÁRIAS (CCA)",
    "unidade_coordenacao": "CCA - COORDENAÇÃO DE ZOOTECNIA"
  }
]